{
"meta":{"test_sets":[],"test_metrics":[],"learn_metrics":[{"best_value":"Min","name":"Logloss"}],"launch_mode":"Train","parameters":"","iteration_count":1000,"learn_sets":["learn"],"name":"experiment"},
"iterations":[
{"learn":[0.6705944976],"iteration":0,"passed_time":0.003926519681,"remaining_time":3.922593161},
{"learn":[0.639757614],"iteration":1,"passed_time":0.007012494469,"remaining_time":3.49923474},
{"learn":[0.6177063499],"iteration":2,"passed_time":0.009865375491,"remaining_time":3.278593121},
{"learn":[0.5936356001],"iteration":3,"passed_time":0.01302699863,"remaining_time":3.243722659},
{"learn":[0.570539668],"iteration":4,"passed_time":0.01675397049,"remaining_time":3.334040128},
{"learn":[0.5492440735],"iteration":5,"passed_time":0.02016856292,"remaining_time":3.34125859},
{"learn":[0.5330826011],"iteration":6,"passed_time":0.0234678513,"remaining_time":3.329082335},
{"learn":[0.5192036382],"iteration":7,"passed_time":0.02637356346,"remaining_time":3.270321869},
{"learn":[0.5036691054],"iteration":8,"passed_time":0.04308400299,"remaining_time":4.74402744},
{"learn":[0.4965345157],"iteration":9,"passed_time":0.04653138231,"remaining_time":4.606606848},
{"learn":[0.4856116575],"iteration":10,"passed_time":0.04968931382,"remaining_time":4.467521033},
{"learn":[0.4800873902],"iteration":11,"passed_time":0.05298132341,"remaining_time":4.362128961},
{"learn":[0.4761242771],"iteration":12,"passed_time":0.05562613788,"remaining_time":4.223307545},
{"learn":[0.4654941662],"iteration":13,"passed_time":0.05914388783,"remaining_time":4.165419529},
{"learn":[0.4560129606],"iteration":14,"passed_time":0.06352862311,"remaining_time":4.171712918},
{"learn":[0.4471647428],"iteration":15,"passed_time":0.06681824817,"remaining_time":4.109322263},
{"learn":[0.443401646],"iteration":16,"passed_time":0.06993314577,"remaining_time":4.043781311},
{"learn":[0.4374623615],"iteration":17,"passed_time":0.07536553113,"remaining_time":4.111608421},
{"learn":[0.4306536736],"iteration":18,"passed_time":0.07921131461,"remaining_time":4.089805244},
{"learn":[0.4272670979],"iteration":19,"passed_time":0.08240805777,"remaining_time":4.037994831},
{"learn":[0.4222519234],"iteration":20,"passed_time":0.08580192193,"remaining_time":4.000003884},
{"learn":[0.4165132707],"iteration":21,"passed_time":0.08903996657,"remaining_time":3.958231241},
{"learn":[0.4116225776],"iteration":22,"passed_time":0.1036299063,"remaining_time":4.402018192},
{"learn":[0.4093421944],"iteration":23,"passed_time":0.1065612409,"remaining_time":4.333490465},
{"learn":[0.4052700202],"iteration":24,"passed_time":0.1097114182,"remaining_time":4.278745308},
{"learn":[0.4044008276],"iteration":25,"passed_time":0.1122021721,"remaining_time":4.203265985},
{"learn":[0.4000793639],"iteration":26,"passed_time":0.1155298933,"remaining_time":4.163355042},
{"learn":[0.3964728104],"iteration":27,"passed_time":0.155358024,"remaining_time":5.393142833},
{"learn":[0.3941442473],"iteration":28,"passed_time":0.1595873319,"remaining_time":5.343424114},
{"learn":[0.3913406337],"iteration":29,"passed_time":0.1628221455,"remaining_time":5.264582705},
{"learn":[0.3886918679],"iteration":30,"passed_time":0.1660687135,"remaining_time":5.190986559},
{"learn":[0.3866172554],"iteration":31,"passed_time":0.1689330101,"remaining_time":5.110223556},
{"learn":[0.3845866059],"iteration":32,"passed_time":0.1727394845,"remaining_time":5.061790348},
{"learn":[0.3819476537],"iteration":33,"passed_time":0.1764767183,"remaining_time":5.014014996},
{"learn":[0.3798180083],"iteration":34,"passed_time":0.1802268506,"remaining_time":4.969111739},
{"learn":[0.378042826],"iteration":35,"passed_time":0.1832189875,"remaining_time":4.906197333},
{"learn":[0.3775515226],"iteration":36,"passed_time":0.1886714561,"remaining_time":4.910557088},
{"learn":[0.3765350285],"iteration":37,"passed_time":0.1925137208,"remaining_time":4.873636827},
{"learn":[0.3735221567],"iteration":38,"passed_time":0.195936754,"remaining_time":4.82808258},
{"learn":[0.3732629851],"iteration":39,"passed_time":0.1982880332,"remaining_time":4.758912796},
{"learn":[0.3730907932],"iteration":40,"passed_time":0.2005168174,"remaining_time":4.690137265},
{"learn":[0.3714417892],"iteration":41,"passed_time":0.2038279787,"remaining_time":4.649219132},
{"learn":[0.3692196771],"iteration":42,"passed_time":0.207353703,"remaining_time":4.614825437},
{"learn":[0.3685333959],"iteration":43,"passed_time":0.2104928638,"remaining_time":4.573435859},
{"learn":[0.3669859843],"iteration":44,"passed_time":0.2137106221,"remaining_time":4.535414314},
{"learn":[0.3650918484],"iteration":45,"passed_time":0.2167792991,"remaining_time":4.495814159},
{"learn":[0.3639395727],"iteration":46,"passed_time":0.2201440759,"remaining_time":4.463772432},
{"learn":[0.3630814876],"iteration":47,"passed_time":0.2237731041,"remaining_time":4.438166565},
{"learn":[0.3612479875],"iteration":48,"passed_time":0.2269659778,"remaining_time":4.404992752},
{"learn":[0.3601440687],"iteration":49,"passed_time":0.2299803859,"remaining_time":4.369627333},
{"learn":[0.3594061539],"iteration":50,"passed_time":0.2331467989,"remaining_time":4.338359061},
{"learn":[0.3589484894],"iteration":51,"passed_time":0.2364527591,"remaining_time":4.310715686},
{"learn":[0.3571771161],"iteration":52,"passed_time":0.2398861509,"remaining_time":4.286267639},
{"learn":[0.3568308933],"iteration":53,"passed_time":0.2427817752,"remaining_time":4.253177025},
{"learn":[0.3560929371],"iteration":54,"passed_time":0.2457679442,"remaining_time":4.222740132},
{"learn":[0.3547967216],"iteration":55,"passed_time":0.2492000894,"remaining_time":4.200801506},
{"learn":[0.3535297144],"iteration":56,"passed_time":0.252299284,"remaining_time":4.174003943},
{"learn":[0.3524510328],"iteration":57,"passed_time":0.2560709521,"remaining_time":4.158945463},
{"learn":[0.3514419532],"iteration":58,"passed_time":0.2593434058,"remaining_time":4.13630754},
{"learn":[0.3506085102],"iteration":59,"passed_time":0.262463203,"remaining_time":4.111923514},
{"learn":[0.3496175361],"iteration":60,"passed_time":0.265382926,"remaining_time":4.085156844},
{"learn":[0.348717],"iteration":61,"passed_time":0.2685329237,"remaining_time":4.062643265},
{"learn":[0.3480624012],"iteration":62,"passed_time":0.2721850361,"remaining_time":4.048212363},
{"learn":[0.3478395888],"iteration":63,"passed_time":0.2749208628,"remaining_time":4.020717619},
{"learn":[0.3473968025],"iteration":64,"passed_time":0.2779894345,"remaining_time":3.998771097},
{"learn":[0.3466598086],"iteration":65,"passed_time":0.2812640211,"remaining_time":3.980312056},
{"learn":[0.345886909],"iteration":66,"passed_time":0.2850628452,"remaining_time":3.969606487},
{"learn":[0.345849588],"iteration":67,"passed_time":0.2879125926,"remaining_time":3.946096122},
{"learn":[0.3451631081],"iteration":68,"passed_time":0.2909742105,"remaining_time":3.926043333},
{"learn":[0.3440472738],"iteration":69,"passed_time":0.2941811883,"remaining_time":3.908407216},
{"learn":[0.343495147],"iteration":70,"passed_time":0.2975140516,"remaining_time":3.892824704},
{"learn":[0.3427077092],"iteration":71,"passed_time":0.3011324846,"remaining_time":3.881263135},
{"learn":[0.342174781],"iteration":72,"passed_time":0.3047053213,"remaining_time":3.869340176},
{"learn":[0.3410386743],"iteration":73,"passed_time":0.307962979,"remaining_time":3.8536989},
{"learn":[0.3403568821],"iteration":74,"passed_time":0.3116157245,"remaining_time":3.843260602},
{"learn":[0.340101602],"iteration":75,"passed_time":0.314631703,"remaining_time":3.825259126},
{"learn":[0.338783091],"iteration":76,"passed_time":0.318222109,"remaining_time":3.814532553},
{"learn":[0.33873557],"iteration":77,"passed_time":0.3211864238,"remaining_time":3.79658824},
{"learn":[0.3381326632],"iteration":78,"passed_time":0.3246888339,"remaining_time":3.785296405},
{"learn":[0.3376594815],"iteration":79,"passed_time":0.3278980813,"remaining_time":3.770827935},
{"learn":[0.337073183],"iteration":80,"passed_time":0.330974127,"remaining_time":3.755126207},
{"learn":[0.3368262886],"iteration":81,"passed_time":0.3341760364,"remaining_time":3.741141481},
{"learn":[0.336260276],"iteration":82,"passed_time":0.3376640597,"remaining_time":3.730577624},
{"learn":[0.3352151851],"iteration":83,"passed_time":0.3413141255,"remaining_time":3.721949273},
{"learn":[0.3346002818],"iteration":84,"passed_time":0.3451436032,"remaining_time":3.715369375},
{"learn":[0.3339783058],"iteration":85,"passed_time":0.3499099568,"remaining_time":3.718810471},
{"learn":[0.3339357185],"iteration":86,"passed_time":0.3521113027,"remaining_time":3.69514505},
{"learn":[0.3329820295],"iteration":87,"passed_time":0.3554995778,"remaining_time":3.684268352},
{"learn":[0.3322215477],"iteration":88,"passed_time":0.3588490412,"remaining_time":3.673162658},
{"learn":[0.3322180453],"iteration":89,"passed_time":0.3610637123,"remaining_time":3.650755313},
{"learn":[0.3321263786],"iteration":90,"passed_time":0.3665365236,"remaining_time":3.661337362},
{"learn":[0.3312792044],"iteration":91,"passed_time":0.370155624,"remaining_time":3.653275071},
{"learn":[0.3307874919],"iteration":92,"passed_time":0.3736469447,"remaining_time":3.644062138},
{"learn":[0.3303798979],"iteration":93,"passed_time":0.3767506094,"remaining_time":3.631234597},
{"learn":[0.3293037448],"iteration":94,"passed_time":0.3815458966,"remaining_time":3.634726699},
{"learn":[0.3290895654],"iteration":95,"passed_time":0.3844019996,"remaining_time":3.619785496},
{"learn":[0.3286618496],"iteration":96,"passed_time":0.387643187,"remaining_time":3.608678328},
{"learn":[0.3286469111],"iteration":97,"passed_time":0.3900661281,"remaining_time":3.590200485},
{"learn":[0.3279497259],"iteration":98,"passed_time":0.3931235308,"remaining_time":3.577821225},
{"learn":[0.3273524955],"iteration":99,"passed_time":0.3965688328,"remaining_time":3.569119495},
{"learn":[0.3269926338],"iteration":100,"passed_time":0.3999646727,"remaining_time":3.560081592},
{"learn":[0.3266717344],"iteration":101,"passed_time":0.4030079477,"remaining_time":3.548050363},
{"learn":[0.3264687495],"iteration":102,"passed_time":0.4057755738,"remaining_time":3.533793104},
{"learn":[0.3261317266],"iteration":103,"passed_time":0.4087650402,"remaining_time":3.521668039},
{"learn":[0.3256242067],"iteration":104,"passed_time":0.4124151822,"remaining_time":3.515348458},
{"learn":[0.3256050852],"iteration":105,"passed_time":0.4150121013,"remaining_time":3.500196401},
{"learn":[0.3249324309],"iteration":106,"passed_time":0.4181363484,"remaining_time":3.489679992},
{"learn":[0.3243721984],"iteration":107,"passed_time":0.4212338856,"remaining_time":3.47907987},
{"learn":[0.3236400908],"iteration":108,"passed_time":0.4243576514,"remaining_time":3.468831811},
{"learn":[0.3232145356],"iteration":109,"passed_time":0.4279502599,"remaining_time":3.462506649},
{"learn":[0.322660392],"iteration":110,"passed_time":0.4316626402,"remaining_time":3.457189974},
{"learn":[0.3226204515],"iteration":111,"passed_time":0.4341361511,"remaining_time":3.442079483},
{"learn":[0.3220531508],"iteration":112,"passed_time":0.4371820784,"remaining_time":3.431685872},
{"learn":[0.3216389982],"iteration":113,"passed_time":0.4402994061,"remaining_time":3.421976086},
{"learn":[0.3212074957],"iteration":114,"passed_time":0.4437246502,"remaining_time":3.414750569},
{"learn":[0.3205678356],"iteration":115,"passed_time":0.4469188301,"remaining_time":3.405829706},
{"learn":[0.3202812061],"iteration":116,"passed_time":0.4500261529,"remaining_time":3.396351223},
{"learn":[0.3201412222],"iteration":117,"passed_time":0.4529645206,"remaining_time":3.385717857},
{"learn":[0.3197647808],"iteration":118,"passed_time":0.4560452624,"remaining_time":3.376267867},
{"learn":[0.3193709625],"iteration":119,"passed_time":0.4598104855,"remaining_time":3.37194356},
{"learn":[0.3189426504],"iteration":120,"passed_time":0.4630490077,"remaining_time":3.363802295},
{"learn":[0.3183259273],"iteration":121,"passed_time":0.4660798887,"remaining_time":3.354247068},
{"learn":[0.3177301842],"iteration":122,"passed_time":0.4691969855,"remaining_time":3.345412653},
{"learn":[0.3172516326],"iteration":123,"passed_time":0.4727250181,"remaining_time":3.339573515},
{"learn":[0.3172264175],"iteration":124,"passed_time":0.4756593484,"remaining_time":3.329615439},
{"learn":[0.3169428751],"iteration":125,"passed_time":0.4789338181,"remaining_time":3.32212823},
{"learn":[0.3164397986],"iteration":126,"passed_time":0.4820565487,"remaining_time":3.313664307},
{"learn":[0.3161710754],"iteration":127,"passed_time":0.4851471437,"remaining_time":3.305064917},
{"learn":[0.3157094776],"iteration":128,"passed_time":0.488622232,"remaining_time":3.299147009},
{"learn":[0.3152563728],"iteration":129,"passed_time":0.4922957074,"remaining_time":3.29459435},
{"learn":[0.3148024055],"iteration":130,"passed_time":0.495395188,"remaining_time":3.286247469},
{"learn":[0.314467388],"iteration":131,"passed_time":0.4986860373,"remaining_time":3.279238488},
{"learn":[0.313913935],"iteration":132,"passed_time":0.501778184,"remaining_time":3.270990117},
{"learn":[0.3136747889],"iteration":133,"passed_time":0.5051668732,"remaining_time":3.264735166},
{"learn":[0.3129718023],"iteration":134,"passed_time":0.5091521265,"remaining_time":3.262345107},
{"learn":[0.3125868491],"iteration":135,"passed_time":0.5124301689,"remaining_time":3.25543872},
{"learn":[0.3121396181],"iteration":136,"passed_time":0.5156786773,"remaining_time":3.248399259},
{"learn":[0.3117895659],"iteration":137,"passed_time":0.5193182511,"remaining_time":3.243857481},
{"learn":[0.3115099068],"iteration":138,"passed_time":0.5227845089,"remaining_time":3.238255123},
{"learn":[0.3112915162],"iteration":139,"passed_time":0.5260026187,"remaining_time":3.231158944},
{"learn":[0.3109723334],"iteration":140,"passed_time":0.5293174323,"remaining_time":3.22470691},
{"learn":[0.3107845511],"iteration":141,"passed_time":0.5325754163,"remaining_time":3.217955684},
{"learn":[0.3103847876],"iteration":142,"passed_time":0.5358021597,"remaining_time":3.21106609},
{"learn":[0.3099166823],"iteration":143,"passed_time":0.5396898379,"remaining_time":3.208156258},
{"learn":[0.3095319597],"iteration":144,"passed_time":0.5428618009,"remaining_time":3.201012688},
{"learn":[0.3092178127],"iteration":145,"passed_time":0.5462673128,"remaining_time":3.195289624},
{"learn":[0.308758492],"iteration":146,"passed_time":0.5507638458,"remaining_time":3.195928983},
{"learn":[0.3083385357],"iteration":147,"passed_time":0.5541867572,"remaining_time":3.190318359},
{"learn":[0.3079734003],"iteration":148,"passed_time":0.5574880516,"remaining_time":3.184042496},
{"learn":[0.3076975546],"iteration":149,"passed_time":0.5610858886,"remaining_time":3.179486702},
{"learn":[0.3074181083],"iteration":150,"passed_time":0.5646790924,"remaining_time":3.174917546},
{"learn":[0.3067466622],"iteration":151,"passed_time":0.5679937754,"remaining_time":3.168807379},
{"learn":[0.3063768273],"iteration":152,"passed_time":0.5715216592,"remaining_time":3.163914022},
{"learn":[0.3059950199],"iteration":153,"passed_time":0.5747947032,"remaining_time":3.157638435},
{"learn":[0.3058308734],"iteration":154,"passed_time":0.5781681409,"remaining_time":3.151948897},
{"learn":[0.3053317038],"iteration":155,"passed_time":0.5813112935,"remaining_time":3.145043152},
{"learn":[0.3048627486],"iteration":156,"passed_time":0.584409307,"remaining_time":3.137942967},
{"learn":[0.3045414464],"iteration":157,"passed_time":0.5878870654,"remaining_time":3.132917146},
{"learn":[0.3042824696],"iteration":158,"passed_time":0.5910430854,"remaining_time":3.126209024},
{"learn":[0.3039564367],"iteration":159,"passed_time":0.5943920299,"remaining_time":3.120558157},
{"learn":[0.303424672],"iteration":160,"passed_time":0.597640892,"remaining_time":3.114414338},
{"learn":[0.3029874948],"iteration":161,"passed_time":0.6009033217,"remaining_time":3.108376442},
{"learn":[0.3026904579],"iteration":162,"passed_time":0.6044353672,"remaining_time":3.10375707},
{"learn":[0.3023130466],"iteration":163,"passed_time":0.6077964279,"remaining_time":3.098279352},
{"learn":[0.3019629217],"iteration":164,"passed_time":0.6109949582,"remaining_time":3.092004788},
{"learn":[0.3015833276],"iteration":165,"passed_time":0.6142081535,"remaining_time":3.085840964},
{"learn":[0.3011379475],"iteration":166,"passed_time":0.6176221531,"remaining_time":3.080714093},
{"learn":[0.3004613516],"iteration":167,"passed_time":0.6207882795,"remaining_time":3.074380051},
{"learn":[0.3001712238],"iteration":168,"passed_time":0.6241408737,"remaining_time":3.069000391},
{"learn":[0.299913417],"iteration":169,"passed_time":0.6275292052,"remaining_time":3.063819061},
{"learn":[0.2997077006],"iteration":170,"passed_time":0.6307394157,"remaining_time":3.057795179},
{"learn":[0.2995386767],"iteration":171,"passed_time":0.6348758243,"remaining_time":3.056262689},
{"learn":[0.2993879376],"iteration":172,"passed_time":0.6384998227,"remaining_time":3.052250598},
{"learn":[0.2992172016],"iteration":173,"passed_time":0.6417427856,"remaining_time":3.046434143},
{"learn":[0.2984607415],"iteration":174,"passed_time":0.6448023362,"remaining_time":3.039782442},
{"learn":[0.2979775234],"iteration":175,"passed_time":0.6478952867,"remaining_time":3.033327933},
{"learn":[0.29776079],"iteration":176,"passed_time":0.6524735774,"remaining_time":3.03381782},
{"learn":[0.2974560248],"iteration":177,"passed_time":0.6555616258,"remaining_time":3.027368856},
{"learn":[0.2972628907],"iteration":178,"passed_time":0.6586674607,"remaining_time":3.021039024},
{"learn":[0.2971743943],"iteration":179,"passed_time":0.6623041533,"remaining_time":3.017163365},
{"learn":[0.2967228511],"iteration":180,"passed_time":0.666152124,"remaining_time":3.014246351},
{"learn":[0.2960400673],"iteration":181,"passed_time":0.6693545826,"remaining_time":3.008417849},
{"learn":[0.2958677473],"iteration":182,"passed_time":0.6724701137,"remaining_time":3.002229961},
{"learn":[0.2957109323],"iteration":183,"passed_time":0.6756971493,"remaining_time":2.996569967},
{"learn":[0.2955305212],"iteration":184,"passed_time":0.6790753677,"remaining_time":2.991602296},
{"learn":[0.2954184386],"iteration":185,"passed_time":0.6829847865,"remaining_time":2.988976431},
{"learn":[0.2952485828],"iteration":186,"passed_time":0.6862340151,"remaining_time":2.9834666},
{"learn":[0.2947179305],"iteration":187,"passed_time":0.6893950926,"remaining_time":2.977600081},
{"learn":[0.2944471563],"iteration":188,"passed_time":0.6927380243,"remaining_time":2.972542528},
{"learn":[0.2939136846],"iteration":189,"passed_time":0.696071177,"remaining_time":2.967461334},
{"learn":[0.2935913952],"iteration":190,"passed_time":0.6994587756,"remaining_time":2.962629055},
{"learn":[0.2932224441],"iteration":191,"passed_time":0.7026885088,"remaining_time":2.957147474},
{"learn":[0.293104941],"iteration":192,"passed_time":0.7055292988,"remaining_time":2.950062923},
{"learn":[0.2930004824],"iteration":193,"passed_time":0.7089255309,"remaining_time":2.945329783},
{"learn":[0.2923513321],"iteration":194,"passed_time":0.7127377278,"remaining_time":2.942327543},
{"learn":[0.2923014194],"iteration":195,"passed_time":0.715873466,"remaining_time":2.936542177},
{"learn":[0.2921311946],"iteration":196,"passed_time":0.7190593565,"remaining_time":2.930988138},
{"learn":[0.2920067274],"iteration":197,"passed_time":0.7222042954,"remaining_time":2.925292146},
{"learn":[0.2919007931],"iteration":198,"passed_time":0.7253088531,"remaining_time":2.919459253},
{"learn":[0.2918086676],"iteration":199,"passed_time":0.7293743613,"remaining_time":2.917497445},
{"learn":[0.2914050104],"iteration":200,"passed_time":0.7327762484,"remaining_time":2.912876729},
{"learn":[0.2912778689],"iteration":201,"passed_time":0.7360062908,"remaining_time":2.907589208},
{"learn":[0.2907443565],"iteration":202,"passed_time":0.7391671736,"remaining_time":2.90205043},
{"learn":[0.2905601108],"iteration":203,"passed_time":0.7428910255,"remaining_time":2.898731648},
{"learn":[0.2902279302],"iteration":204,"passed_time":0.7466615333,"remaining_time":2.895589849},
{"learn":[0.2900489756],"iteration":205,"passed_time":0.7498953735,"remaining_time":2.89037343},
{"learn":[0.2898121402],"iteration":206,"passed_time":0.7530996487,"remaining_time":2.885062906},
{"learn":[0.2893764843],"iteration":207,"passed_time":0.756642037,"remaining_time":2.881060064},
{"learn":[0.2892670577],"iteration":208,"passed_time":0.7601622739,"remaining_time":2.876977793},
{"learn":[0.2891174608],"iteration":209,"passed_time":0.7632083517,"remaining_time":2.871117133},
{"learn":[0.2888997287],"iteration":210,"passed_time":0.7670907016,"remaining_time":2.868410254},
{"learn":[0.2887728122],"iteration":211,"passed_time":0.7702976097,"remaining_time":2.863181681},
{"learn":[0.288395044],"iteration":212,"passed_time":0.7737242036,"remaining_time":2.858783794},
{"learn":[0.2880791316],"iteration":213,"passed_time":0.7773360832,"remaining_time":2.855075521},
{"learn":[0.2876910035],"iteration":214,"passed_time":0.7805516697,"remaining_time":2.849921213},
{"learn":[0.2875961626],"iteration":215,"passed_time":0.783795788,"remaining_time":2.844888416},
{"learn":[0.2871347133],"iteration":216,"passed_time":0.7870676808,"remaining_time":2.839972323},
{"learn":[0.2867975462],"iteration":217,"passed_time":0.7901003954,"remaining_time":2.834213345},
{"learn":[0.2866385804],"iteration":218,"passed_time":0.7934051887,"remaining_time":2.829449554},
{"learn":[0.2864651099],"iteration":219,"passed_time":0.7964040165,"remaining_time":2.82361424},
{"learn":[0.2862674179],"iteration":220,"passed_time":0.800011208,"remaining_time":2.819949009},
{"learn":[0.2860352635],"iteration":221,"passed_time":0.8034949837,"remaining_time":2.81585179},
{"learn":[0.2856164598],"iteration":222,"passed_time":0.8073617409,"remaining_time":2.813094496},
{"learn":[0.2852484821],"iteration":223,"passed_time":0.8104130135,"remaining_time":2.807502225},
{"learn":[0.2848788983],"iteration":224,"passed_time":0.8137654493,"remaining_time":2.802969881},
{"learn":[0.2847883136],"iteration":225,"passed_time":0.8170726081,"remaining_time":2.798292914},
{"learn":[0.2846899446],"iteration":226,"passed_time":0.820148796,"remaining_time":2.792841495},
{"learn":[0.284293826],"iteration":227,"passed_time":0.8252445926,"remaining_time":2.794249235},
{"learn":[0.283956562],"iteration":228,"passed_time":0.8287019673,"remaining_time":2.790083916},
{"learn":[0.2838344197],"iteration":229,"passed_time":0.8319412146,"remaining_time":2.785194501},
{"learn":[0.2837232851],"iteration":230,"passed_time":0.8349742011,"remaining_time":2.77963273},
{"learn":[0.2836181123],"iteration":231,"passed_time":0.8380310376,"remaining_time":2.774171711},
{"learn":[0.2835176964],"iteration":232,"passed_time":0.8415885953,"remaining_time":2.770379625},
{"learn":[0.2834317575],"iteration":233,"passed_time":0.8457267903,"remaining_time":2.768490262},
{"learn":[0.2833747944],"iteration":234,"passed_time":0.8490459596,"remaining_time":2.763915571},
{"learn":[0.2831009667],"iteration":235,"passed_time":0.8521898082,"remaining_time":2.758783955},
{"learn":[0.2826785603],"iteration":236,"passed_time":0.8561695798,"remaining_time":2.756360293},
{"learn":[0.2823726478],"iteration":237,"passed_time":0.859612583,"remaining_time":2.752204993},
{"learn":[0.282253106],"iteration":238,"passed_time":0.8627791323,"remaining_time":2.747175396},
{"learn":[0.2820199104],"iteration":239,"passed_time":0.8658459621,"remaining_time":2.741845547},
{"learn":[0.2819362418],"iteration":240,"passed_time":0.8690483946,"remaining_time":2.736961541},
{"learn":[0.2816591292],"iteration":241,"passed_time":0.8721978501,"remaining_time":2.731925497},
{"learn":[0.2815773992],"iteration":242,"passed_time":0.8762812924,"remaining_time":2.729814561},
{"learn":[0.2814000712],"iteration":243,"passed_time":0.8799412768,"remaining_time":2.726375432},
{"learn":[0.2811770015],"iteration":244,"passed_time":0.8831038953,"remaining_time":2.7214018},
{"learn":[0.2808296576],"iteration":245,"passed_time":0.8869479895,"remaining_time":2.718531643},
{"learn":[0.2805475209],"iteration":246,"passed_time":0.8904568443,"remaining_time":2.714631594},
{"learn":[0.2804096486],"iteration":247,"passed_time":0.8935827803,"remaining_time":2.709573592},
{"learn":[0.2801394393],"iteration":248,"passed_time":0.896631493,"remaining_time":2.704298198},
{"learn":[0.2800146291],"iteration":249,"passed_time":0.8997908693,"remaining_time":2.699372608},
{"learn":[0.2799415652],"iteration":250,"passed_time":0.9030097403,"remaining_time":2.694638627},
{"learn":[0.2795116797],"iteration":251,"passed_time":0.9067513547,"remaining_time":2.691468307},
{"learn":[0.2792619457],"iteration":252,"passed_time":0.9099647402,"remaining_time":2.686733838},
{"learn":[0.2791550472],"iteration":253,"passed_time":0.9130893281,"remaining_time":2.681750546},
{"learn":[0.2788774284],"iteration":254,"passed_time":0.9168027261,"remaining_time":2.678502082},
{"learn":[0.2788094024],"iteration":255,"passed_time":0.9203185492,"remaining_time":2.674675784},
{"learn":[0.2787102533],"iteration":256,"passed_time":0.9234336864,"remaining_time":2.669693498},
{"learn":[0.2785760876],"iteration":257,"passed_time":0.9268030706,"remaining_time":2.665456893},
{"learn":[0.278325907],"iteration":258,"passed_time":0.9300485221,"remaining_time":2.660872413},
{"learn":[0.2782349031],"iteration":259,"passed_time":0.9336781543,"remaining_time":2.65739167},
{"learn":[0.2781707273],"iteration":260,"passed_time":0.9370733691,"remaining_time":2.653246053},
{"learn":[0.2780105746],"iteration":261,"passed_time":0.9405928125,"remaining_time":2.64945609},
{"learn":[0.277754621],"iteration":262,"passed_time":0.9437588138,"remaining_time":2.644677741},
{"learn":[0.2775214819],"iteration":263,"passed_time":0.9474109449,"remaining_time":2.641266877},
{"learn":[0.2774479662],"iteration":264,"passed_time":0.9513677612,"remaining_time":2.638699262},
{"learn":[0.2770831204],"iteration":265,"passed_time":0.9545113064,"remaining_time":2.633877063},
{"learn":[0.2768954547],"iteration":266,"passed_time":0.9581607996,"remaining_time":2.630456427},
{"learn":[0.2766508062],"iteration":267,"passed_time":0.9613966678,"remaining_time":2.625904332},
{"learn":[0.2764965129],"iteration":268,"passed_time":0.9650818221,"remaining_time":2.622582944},
{"learn":[0.2763221316],"iteration":269,"passed_time":0.968200937,"remaining_time":2.617728459},
{"learn":[0.2761038613],"iteration":270,"passed_time":0.9714618448,"remaining_time":2.61326821},
{"learn":[0.2759195679],"iteration":271,"passed_time":0.9745687962,"remaining_time":2.608404719},
{"learn":[0.2757185835],"iteration":272,"passed_time":0.9776071056,"remaining_time":2.603371303},
{"learn":[0.2753629562],"iteration":273,"passed_time":0.9812860909,"remaining_time":2.600050007},
{"learn":[0.2751290584],"iteration":274,"passed_time":0.9843654531,"remaining_time":2.595145285},
{"learn":[0.2750653715],"iteration":275,"passed_time":0.9874011537,"remaining_time":2.590139258},
{"learn":[0.2747610187],"iteration":276,"passed_time":0.9905366672,"remaining_time":2.58540798},
{"learn":[0.2745787948],"iteration":277,"passed_time":0.9942681441,"remaining_time":2.582235971},
{"learn":[0.274478439],"iteration":278,"passed_time":0.9979945244,"remaining_time":2.579046782},
{"learn":[0.2744184855],"iteration":279,"passed_time":1.001264948,"remaining_time":2.574681294},
{"learn":[0.274284754],"iteration":280,"passed_time":1.004455607,"remaining_time":2.570119507},
{"learn":[0.274179956],"iteration":281,"passed_time":1.007817195,"remaining_time":2.566002645},
{"learn":[0.273797421],"iteration":282,"passed_time":1.011237587,"remaining_time":2.562040106},
{"learn":[0.2735837532],"iteration":283,"passed_time":1.014340654,"remaining_time":2.557281366},
{"learn":[0.2734018229],"iteration":284,"passed_time":1.017438675,"remaining_time":2.552521587},
{"learn":[0.2731153054],"iteration":285,"passed_time":1.020529151,"remaining_time":2.547754594},
{"learn":[0.2730456107],"iteration":286,"passed_time":1.023696232,"remaining_time":2.543189593},
{"learn":[0.2727794315],"iteration":287,"passed_time":1.027134385,"remaining_time":2.539304452},
{"learn":[0.2726622318],"iteration":288,"passed_time":1.030314979,"remaining_time":2.534788756},
{"learn":[0.2725277856],"iteration":289,"passed_time":1.033709891,"remaining_time":2.530806974},
{"learn":[0.2724976578],"iteration":290,"passed_time":1.037652055,"remaining_time":2.528162566},
{"learn":[0.2724345727],"iteration":291,"passed_time":1.040856703,"remaining_time":2.523721048},
{"learn":[0.2722643609],"iteration":292,"passed_time":1.044276707,"remaining_time":2.519807617},
{"learn":[0.2721272525],"iteration":293,"passed_time":1.047416406,"remaining_time":2.515224431},
{"learn":[0.2719774275],"iteration":294,"passed_time":1.050740796,"remaining_time":2.511092412},
{"learn":[0.2718795486],"iteration":295,"passed_time":1.053889795,"remaining_time":2.506548702},
{"learn":[0.2717909455],"iteration":296,"passed_time":1.056924453,"remaining_time":2.501743738},
{"learn":[0.2717201949],"iteration":297,"passed_time":1.060396201,"remaining_time":2.497980312},
{"learn":[0.2714742516],"iteration":298,"passed_time":1.063455506,"remaining_time":2.493251872},
{"learn":[0.2711626438],"iteration":299,"passed_time":1.066711211,"remaining_time":2.488992826},
{"learn":[0.2711125791],"iteration":300,"passed_time":1.069931103,"remaining_time":2.484657279},
{"learn":[0.2710699969],"iteration":301,"passed_time":1.07318689,"remaining_time":2.480412083},
{"learn":[0.2709919848],"iteration":302,"passed_time":1.076366412,"remaining_time":2.475997983},
{"learn":[0.2707665375],"iteration":303,"passed_time":1.079928453,"remaining_time":2.472467775},
{"learn":[0.270622601],"iteration":304,"passed_time":1.083049545,"remaining_time":2.467932569},
{"learn":[0.2705161656],"iteration":305,"passed_time":1.086242774,"remaining_time":2.463570213},
{"learn":[0.2704738412],"iteration":306,"passed_time":1.089335511,"remaining_time":2.458988629},
{"learn":[0.2703401596],"iteration":307,"passed_time":1.092826071,"remaining_time":2.455310523},
{"learn":[0.2702018364],"iteration":308,"passed_time":1.097077849,"remaining_time":2.453335901},
{"learn":[0.2699697243],"iteration":309,"passed_time":1.100262867,"remaining_time":2.448972187},
{"learn":[0.2698528314],"iteration":310,"passed_time":1.103458329,"remaining_time":2.444639191},
{"learn":[0.2695725717],"iteration":311,"passed_time":1.106896172,"remaining_time":2.440847969},
{"learn":[0.2695448709],"iteration":312,"passed_time":1.110370073,"remaining_time":2.437138147},
{"learn":[0.2694702389],"iteration":313,"passed_time":1.113417107,"remaining_time":2.432497247},
{"learn":[0.2693635077],"iteration":314,"passed_time":1.116686755,"remaining_time":2.428350563},
{"learn":[0.2692453866],"iteration":315,"passed_time":1.119790265,"remaining_time":2.423849815},
{"learn":[0.2691530811],"iteration":316,"passed_time":1.12344266,"remaining_time":2.420540494},
{"learn":[0.2689442134],"iteration":317,"passed_time":1.12672108,"remaining_time":2.41642697},
{"learn":[0.2687932918],"iteration":318,"passed_time":1.129836053,"remaining_time":2.411969757},
{"learn":[0.2686892185],"iteration":319,"passed_time":1.132859248,"remaining_time":2.407325902},
{"learn":[0.268625032],"iteration":320,"passed_time":1.135938709,"remaining_time":2.402811163},
{"learn":[0.2683660162],"iteration":321,"passed_time":1.140060864,"remaining_time":2.400500826},
{"learn":[0.2683118712],"iteration":322,"passed_time":1.14333473,"remaining_time":2.396401277},
{"learn":[0.2681893004],"iteration":323,"passed_time":1.146465167,"remaining_time":2.39200757},
{"learn":[0.268066193],"iteration":324,"passed_time":1.15006839,"remaining_time":2.38860358},
{"learn":[0.2679968058],"iteration":325,"passed_time":1.154226287,"remaining_time":2.386345146},
{"learn":[0.2679315562],"iteration":326,"passed_time":1.157843848,"remaining_time":2.382963027},
{"learn":[0.2678918111],"iteration":327,"passed_time":1.160976996,"remaining_time":2.378587017},
{"learn":[0.267761282],"iteration":328,"passed_time":1.164181068,"remaining_time":2.374363211},
{"learn":[0.267723116],"iteration":329,"passed_time":1.167285367,"remaining_time":2.369943017},
{"learn":[0.2675956774],"iteration":330,"passed_time":1.171396549,"remaining_time":2.367565835},
{"learn":[0.267547721],"iteration":331,"passed_time":1.17450436,"remaining_time":2.363159376},
{"learn":[0.2674885364],"iteration":332,"passed_time":1.177521974,"remaining_time":2.35858005},
{"learn":[0.267420388],"iteration":333,"passed_time":1.180590599,"remaining_time":2.354111792},
{"learn":[0.267257047],"iteration":334,"passed_time":1.184344599,"remaining_time":2.351012413},
{"learn":[0.2671552933],"iteration":335,"passed_time":1.189952615,"remaining_time":2.351573026},
{"learn":[0.2669955368],"iteration":336,"passed_time":1.193359657,"remaining_time":2.347766922},
{"learn":[0.2669328717],"iteration":337,"passed_time":1.196451134,"remaining_time":2.343345121},
{"learn":[0.2668542059],"iteration":338,"passed_time":1.200063722,"remaining_time":2.339947257},
{"learn":[0.266707372],"iteration":339,"passed_time":1.203236556,"remaining_time":2.33569449},
{"learn":[0.2665731064],"iteration":340,"passed_time":1.206359467,"remaining_time":2.33135158},
{"learn":[0.2665119756],"iteration":341,"passed_time":1.209427627,"remaining_time":2.326910464},
{"learn":[0.2663551447],"iteration":342,"passed_time":1.212724394,"remaining_time":2.322915239},
{"learn":[0.2661657227],"iteration":343,"passed_time":1.216837444,"remaining_time":2.320480708},
{"learn":[0.2659266359],"iteration":344,"passed_time":1.22019052,"remaining_time":2.316593595},
{"learn":[0.2657622433],"iteration":345,"passed_time":1.223414681,"remaining_time":2.312465899},
{"learn":[0.2657112371],"iteration":346,"passed_time":1.22737512,"remaining_time":2.309728972},
{"learn":[0.265549148],"iteration":347,"passed_time":1.230899544,"remaining_time":2.306168111},
{"learn":[0.2653475152],"iteration":348,"passed_time":1.234238806,"remaining_time":2.302262071},
{"learn":[0.2651763054],"iteration":349,"passed_time":1.237777616,"remaining_time":2.298729859},
{"learn":[0.2651414159],"iteration":350,"passed_time":1.241425545,"remaining_time":2.295399369},
{"learn":[0.2650993511],"iteration":351,"passed_time":1.244790286,"remaining_time":2.291545753},
{"learn":[0.2650418916],"iteration":352,"passed_time":1.248826856,"remaining_time":2.288926277},
{"learn":[0.2648808303],"iteration":353,"passed_time":1.252050903,"remaining_time":2.284816055},
{"learn":[0.2647674971],"iteration":354,"passed_time":1.255106179,"remaining_time":2.280404185},
{"learn":[0.2646916816],"iteration":355,"passed_time":1.258963831,"remaining_time":2.277451424},
{"learn":[0.2646525185],"iteration":356,"passed_time":1.262374417,"remaining_time":2.273688375},
{"learn":[0.2646134365],"iteration":357,"passed_time":1.265518414,"remaining_time":2.269449222},
{"learn":[0.2645342661],"iteration":358,"passed_time":1.268721824,"remaining_time":2.265322254},
{"learn":[0.2643187888],"iteration":359,"passed_time":1.272141569,"remaining_time":2.261585012},
{"learn":[0.2642884531],"iteration":360,"passed_time":1.275266166,"remaining_time":2.257327091},
{"learn":[0.2641660321],"iteration":361,"passed_time":1.27874086,"remaining_time":2.253692456},
{"learn":[0.2641303332],"iteration":362,"passed_time":1.281880862,"remaining_time":2.249471374},
{"learn":[0.2640732929],"iteration":363,"passed_time":1.303155977,"remaining_time":2.276942861},
{"learn":[0.2640346123],"iteration":364,"passed_time":1.307041933,"remaining_time":2.27389487},
{"learn":[0.2640160055],"iteration":365,"passed_time":1.311064707,"remaining_time":2.271079301},
{"learn":[0.2639830691],"iteration":366,"passed_time":1.314858954,"remaining_time":2.267862991},
{"learn":[0.263881201],"iteration":367,"passed_time":1.319096869,"remaining_time":2.265405492},
{"learn":[0.263857055],"iteration":368,"passed_time":1.322127158,"remaining_time":2.26087327},
{"learn":[0.2637230324],"iteration":369,"passed_time":1.32524371,"remaining_time":2.256496047},
{"learn":[0.2636889002],"iteration":370,"passed_time":1.329177096,"remaining_time":2.253510494},
{"learn":[0.2636461991],"iteration":371,"passed_time":1.332862397,"remaining_time":2.250101037},
{"learn":[0.2635161969],"iteration":372,"passed_time":1.335975436,"remaining_time":2.245728146},
{"learn":[0.2634716433],"iteration":373,"passed_time":1.339411614,"remaining_time":2.241902862},
{"learn":[0.2632755674],"iteration":374,"passed_time":1.342802823,"remaining_time":2.238004705},
{"learn":[0.2631673183],"iteration":375,"passed_time":1.34631912,"remaining_time":2.234316838},
{"learn":[0.2631198114],"iteration":376,"passed_time":1.349499965,"remaining_time":2.230075538},
{"learn":[0.2630898739],"iteration":377,"passed_time":1.352619436,"remaining_time":2.225738861},
{"learn":[0.2629039949],"iteration":378,"passed_time":1.355702915,"remaining_time":2.221349631},
{"learn":[0.2628300381],"iteration":379,"passed_time":1.359074178,"remaining_time":2.217436817},
{"learn":[0.2626608952],"iteration":380,"passed_time":1.362539477,"remaining_time":2.213679623},
{"learn":[0.2625435856],"iteration":381,"passed_time":1.365580893,"remaining_time":2.209238199},
{"learn":[0.2623649069],"iteration":382,"passed_time":1.368708073,"remaining_time":2.204942248},
{"learn":[0.2622723589],"iteration":383,"passed_time":1.372299042,"remaining_time":2.20139638},
{"learn":[0.2620520257],"iteration":384,"passed_time":1.376330811,"remaining_time":2.198554413},
{"learn":[0.2619926753],"iteration":385,"passed_time":1.37957565,"remaining_time":2.194454532},
{"learn":[0.2619565924],"iteration":386,"passed_time":1.382622893,"remaining_time":2.190046081},
{"learn":[0.2618184352],"iteration":387,"passed_time":1.387215302,"remaining_time":2.188081868},
{"learn":[0.2616605362],"iteration":388,"passed_time":1.39096919,"remaining_time":2.184787083},
{"learn":[0.2615858563],"iteration":389,"passed_time":1.394059602,"remaining_time":2.180452199},
{"learn":[0.2615575791],"iteration":390,"passed_time":1.397417321,"remaining_time":2.176540021},
{"learn":[0.2615328837],"iteration":391,"passed_time":1.400723859,"remaining_time":2.172551291},
{"learn":[0.2615048249],"iteration":392,"passed_time":1.40436354,"remaining_time":2.169080582},
{"learn":[0.2613755447],"iteration":393,"passed_time":1.408580481,"remaining_time":2.166496882},
{"learn":[0.2612297119],"iteration":394,"passed_time":1.412121656,"remaining_time":2.162869878},
{"learn":[0.2611627221],"iteration":395,"passed_time":1.415354912,"remaining_time":2.158773654},
{"learn":[0.2611126085],"iteration":396,"passed_time":1.41864744,"remaining_time":2.154771805},
{"learn":[0.2610716989],"iteration":397,"passed_time":1.422946696,"remaining_time":2.152296259},
{"learn":[0.2609681412],"iteration":398,"passed_time":1.426304566,"remaining_time":2.148393594},
{"learn":[0.2608681349],"iteration":399,"passed_time":1.429710992,"remaining_time":2.144566488},
{"learn":[0.2607714027],"iteration":400,"passed_time":1.432838177,"remaining_time":2.140324359},
{"learn":[0.2606526135],"iteration":401,"passed_time":1.436293444,"remaining_time":2.136575819},
{"learn":[0.2605613225],"iteration":402,"passed_time":1.439960974,"remaining_time":2.13314318},
{"learn":[0.2605044987],"iteration":403,"passed_time":1.443059946,"remaining_time":2.128870613},
{"learn":[0.2604412355],"iteration":404,"passed_time":1.446308446,"remaining_time":2.124823519},
{"learn":[0.2604176398],"iteration":405,"passed_time":1.449779711,"remaining_time":2.121106277},
{"learn":[0.2603091439],"iteration":406,"passed_time":1.452819869,"remaining_time":2.116762119},
{"learn":[0.2602261849],"iteration":407,"passed_time":1.456081334,"remaining_time":2.112745465},
{"learn":[0.2601274302],"iteration":408,"passed_time":1.459173131,"remaining_time":2.108487336},
{"learn":[0.2599990089],"iteration":409,"passed_time":1.466779838,"remaining_time":2.110731962},
{"learn":[0.2599223632],"iteration":410,"passed_time":1.471184403,"remaining_time":2.108339691},
{"learn":[0.2598841682],"iteration":411,"passed_time":1.474334636,"remaining_time":2.10414749},
{"learn":[0.2598663612],"iteration":412,"passed_time":1.477613294,"remaining_time":2.100142866},
{"learn":[0.2598431372],"iteration":413,"passed_time":1.480638132,"remaining_time":2.095782477},
{"learn":[0.2596869159],"iteration":414,"passed_time":1.48415205,"remaining_time":2.09211795},
{"learn":[0.2596638714],"iteration":415,"passed_time":1.487619441,"remaining_time":2.088388831},
{"learn":[0.259566675],"iteration":416,"passed_time":1.490735655,"remaining_time":2.084169993},
{"learn":[0.2595160918],"iteration":417,"passed_time":1.493929875,"remaining_time":2.080065041},
{"learn":[0.259400779],"iteration":418,"passed_time":1.49705329,"remaining_time":2.075866257},
{"learn":[0.2592625512],"iteration":419,"passed_time":1.500216758,"remaining_time":2.071727904},
{"learn":[0.2591749401],"iteration":420,"passed_time":1.503692818,"remaining_time":2.06802409},
{"learn":[0.2591328519],"iteration":421,"passed_time":1.506920147,"remaining_time":2.063980675},
{"learn":[0.259077739],"iteration":422,"passed_time":1.51020588,"remaining_time":2.060020787},
{"learn":[0.259027293],"iteration":423,"passed_time":1.513432932,"remaining_time":2.05598436},
{"learn":[0.2589920144],"iteration":424,"passed_time":1.516558178,"remaining_time":2.051814006},
{"learn":[0.2589479297],"iteration":425,"passed_time":1.519918922,"remaining_time":2.047965872},
{"learn":[0.258823292],"iteration":426,"passed_time":1.523707723,"remaining_time":2.044694439},
{"learn":[0.2587977647],"iteration":427,"passed_time":1.526860509,"remaining_time":2.040570587},
{"learn":[0.2587678964],"iteration":428,"passed_time":1.530289931,"remaining_time":2.036819466},
{"learn":[0.2586753663],"iteration":429,"passed_time":1.534061331,"remaining_time":2.03352316},
{"learn":[0.2585910757],"iteration":430,"passed_time":1.537233666,"remaining_time":2.029433773},
{"learn":[0.2585663961],"iteration":431,"passed_time":1.540323438,"remaining_time":2.025240075},
{"learn":[0.2584670193],"iteration":432,"passed_time":1.543373025,"remaining_time":2.020998858},
{"learn":[0.2584446196],"iteration":433,"passed_time":1.546736734,"remaining_time":2.017172791},
{"learn":[0.2583729195],"iteration":434,"passed_time":1.550064228,"remaining_time":2.013301813},
{"learn":[0.2583062009],"iteration":435,"passed_time":1.554329172,"remaining_time":2.010645993},
{"learn":[0.2582790259],"iteration":436,"passed_time":1.557498612,"remaining_time":2.006571439},
{"learn":[0.2581916583],"iteration":437,"passed_time":1.560789763,"remaining_time":2.002657185},
{"learn":[0.2581536426],"iteration":438,"passed_time":1.563826637,"remaining_time":1.998420828},
{"learn":[0.2581066558],"iteration":439,"passed_time":1.567426481,"remaining_time":1.99490643},
{"learn":[0.2580859586],"iteration":440,"passed_time":1.570554038,"remaining_time":1.990792987},
{"learn":[0.2580575575],"iteration":441,"passed_time":1.574132085,"remaining_time":1.987252723},
{"learn":[0.2580258518],"iteration":442,"passed_time":1.577548357,"remaining_time":1.983508882},
{"learn":[0.2579134719],"iteration":443,"passed_time":1.5810218,"remaining_time":1.97983811},
{"learn":[0.2578500106],"iteration":444,"passed_time":1.584628349,"remaining_time":1.976334233},
{"learn":[0.2578209293],"iteration":445,"passed_time":1.587720708,"remaining_time":1.972191194},
{"learn":[0.2577806687],"iteration":446,"passed_time":1.590932997,"remaining_time":1.968201224},
{"learn":[0.2577590836],"iteration":447,"passed_time":1.594066139,"remaining_time":1.964117207},
{"learn":[0.2576751102],"iteration":448,"passed_time":1.59802022,"remaining_time":1.961044858},
{"learn":[0.2576480267],"iteration":449,"passed_time":1.601744826,"remaining_time":1.95768812},
{"learn":[0.2575542728],"iteration":450,"passed_time":1.605341994,"remaining_time":1.954174622},
{"learn":[0.2574496666],"iteration":451,"passed_time":1.608944837,"remaining_time":1.950667634},
{"learn":[0.2573291792],"iteration":452,"passed_time":1.612092444,"remaining_time":1.946610523},
{"learn":[0.2572765649],"iteration":453,"passed_time":1.615464326,"remaining_time":1.942827141},
{"learn":[0.2572253621],"iteration":454,"passed_time":1.618689519,"remaining_time":1.938869863},
{"learn":[0.2571428528],"iteration":455,"passed_time":1.621961123,"remaining_time":1.934971164},
{"learn":[0.2571146902],"iteration":456,"passed_time":1.625816975,"remaining_time":1.931769404},
{"learn":[0.2570358399],"iteration":457,"passed_time":1.629953438,"remaining_time":1.928896864},
{"learn":[0.2569611685],"iteration":458,"passed_time":1.633384968,"remaining_time":1.925187947},
{"learn":[0.2569353157],"iteration":459,"passed_time":1.636646986,"remaining_time":1.921281245},
{"learn":[0.2568917194],"iteration":460,"passed_time":1.640908248,"remaining_time":1.918545652},
{"learn":[0.2568222014],"iteration":461,"passed_time":1.645278461,"remaining_time":1.91593033},
{"learn":[0.2567799141],"iteration":462,"passed_time":1.648717256,"remaining_time":1.912227142},
{"learn":[0.2567623056],"iteration":463,"passed_time":1.651844361,"remaining_time":1.908165038},
{"learn":[0.2567250145],"iteration":464,"passed_time":1.655118794,"remaining_time":1.904276462},
{"learn":[0.2566899074],"iteration":465,"passed_time":1.658484695,"remaining_time":1.900495338},
{"learn":[0.256611496],"iteration":466,"passed_time":1.662025088,"remaining_time":1.896915143},
{"learn":[0.2565546396],"iteration":467,"passed_time":1.665215538,"remaining_time":1.892937321},
{"learn":[0.256497136],"iteration":468,"passed_time":1.668346352,"remaining_time":1.888895337},
{"learn":[0.2563918329],"iteration":469,"passed_time":1.671736416,"remaining_time":1.885149575},
{"learn":[0.2563693842],"iteration":470,"passed_time":1.675188472,"remaining_time":1.88147495},
{"learn":[0.2563542351],"iteration":471,"passed_time":1.6787095,"remaining_time":1.877878424},
{"learn":[0.2563346378],"iteration":472,"passed_time":1.681718805,"remaining_time":1.873712072},
{"learn":[0.2562659544],"iteration":473,"passed_time":1.68530221,"remaining_time":1.870187685},
{"learn":[0.2562392613],"iteration":474,"passed_time":1.688446612,"remaining_time":1.866177834},
{"learn":[0.2561691236],"iteration":475,"passed_time":1.691900998,"remaining_time":1.862512863},
{"learn":[0.256086998],"iteration":476,"passed_time":1.69585689,"remaining_time":1.859398645},
{"learn":[0.2560620167],"iteration":477,"passed_time":1.69889861,"remaining_time":1.855282583},
{"learn":[0.2560434387],"iteration":478,"passed_time":1.702038882,"remaining_time":1.851278199},
{"learn":[0.2560104402],"iteration":479,"passed_time":1.705475285,"remaining_time":1.847598225},
{"learn":[0.2559178802],"iteration":480,"passed_time":1.709256931,"remaining_time":1.844291782},
{"learn":[0.2558786108],"iteration":481,"passed_time":1.712347103,"remaining_time":1.840240247},
{"learn":[0.2558118131],"iteration":482,"passed_time":1.715774189,"remaining_time":1.836553324},
{"learn":[0.2557495014],"iteration":483,"passed_time":1.718877,"remaining_time":1.83252176},
{"learn":[0.255700027],"iteration":484,"passed_time":1.721893611,"remaining_time":1.828402495},
{"learn":[0.2556106932],"iteration":485,"passed_time":1.725687271,"remaining_time":1.825109583},
{"learn":[0.25559138],"iteration":486,"passed_time":1.729400181,"remaining_time":1.821729554},
{"learn":[0.2555258092],"iteration":487,"passed_time":1.732488925,"remaining_time":1.817693299},
{"learn":[0.2554986763],"iteration":488,"passed_time":1.735801573,"remaining_time":1.813894896},
{"learn":[0.2554807722],"iteration":489,"passed_time":1.739177035,"remaining_time":1.810163853},
{"learn":[0.2554585811],"iteration":490,"passed_time":1.742285467,"remaining_time":1.806157439},
{"learn":[0.2554380968],"iteration":491,"passed_time":1.745648749,"remaining_time":1.802417814},
{"learn":[0.2554224298],"iteration":492,"passed_time":1.748630723,"remaining_time":1.798287579},
{"learn":[0.2553270511],"iteration":493,"passed_time":1.751734677,"remaining_time":1.794286937},
{"learn":[0.2552411675],"iteration":494,"passed_time":1.755103879,"remaining_time":1.790560523},
{"learn":[0.2551922803],"iteration":495,"passed_time":1.758407952,"remaining_time":1.786769371},
{"learn":[0.2551252048],"iteration":496,"passed_time":1.761675532,"remaining_time":1.782943245},
{"learn":[0.2550554185],"iteration":497,"passed_time":1.765037808,"remaining_time":1.779214819},
{"learn":[0.2550359413],"iteration":498,"passed_time":1.768646354,"remaining_time":1.775735117},
{"learn":[0.2550203372],"iteration":499,"passed_time":1.773547698,"remaining_time":1.773547698},
{"learn":[0.2549506872],"iteration":500,"passed_time":1.776914045,"remaining_time":1.769820576},
{"learn":[0.2548658332],"iteration":501,"passed_time":1.7801172,"remaining_time":1.765933},
{"learn":[0.254798493],"iteration":502,"passed_time":1.78333376,"remaining_time":1.762061389},
{"learn":[0.2547049026],"iteration":503,"passed_time":1.788712567,"remaining_time":1.760320304},
{"learn":[0.2546411792],"iteration":504,"passed_time":1.791939304,"remaining_time":1.756455358},
{"learn":[0.2545846444],"iteration":505,"passed_time":1.795023856,"remaining_time":1.75245412},
{"learn":[0.2545505511],"iteration":506,"passed_time":1.798325742,"remaining_time":1.748667832},
{"learn":[0.2545327112],"iteration":507,"passed_time":1.80219675,"remaining_time":1.745434647},
{"learn":[0.2544486205],"iteration":508,"passed_time":1.805401377,"remaining_time":1.741556142},
{"learn":[0.2544174991],"iteration":509,"passed_time":1.80866199,"remaining_time":1.737734069},
{"learn":[0.2543289489],"iteration":510,"passed_time":1.811859551,"remaining_time":1.733853856},
{"learn":[0.2542777117],"iteration":511,"passed_time":1.814971216,"remaining_time":1.72989444},
{"learn":[0.2542614476],"iteration":512,"passed_time":1.81900453,"remaining_time":1.726813267},
{"learn":[0.2542401216],"iteration":513,"passed_time":1.822197855,"remaining_time":1.722934158},
{"learn":[0.2542227594],"iteration":514,"passed_time":1.825280175,"remaining_time":1.718953174},
{"learn":[0.2541816763],"iteration":515,"passed_time":1.828661165,"remaining_time":1.715255821},
{"learn":[0.2541364201],"iteration":516,"passed_time":1.837757135,"remaining_time":1.716898832},
{"learn":[0.2541231822],"iteration":517,"passed_time":1.841143193,"remaining_time":1.713187296},
{"learn":[0.2541050142],"iteration":518,"passed_time":1.84452952,"remaining_time":1.709477263},
{"learn":[0.2540550901],"iteration":519,"passed_time":1.848219536,"remaining_time":1.706048803},
{"learn":[0.2540004595],"iteration":520,"passed_time":1.852056406,"remaining_time":1.702754354},
{"learn":[0.2539430692],"iteration":521,"passed_time":1.855414426,"remaining_time":1.69901934},
{"learn":[0.2538588899],"iteration":522,"passed_time":1.858987553,"remaining_time":1.695481956},
{"learn":[0.2538317996],"iteration":523,"passed_time":1.862592918,"remaining_time":1.69197372},
{"learn":[0.2538156754],"iteration":524,"passed_time":1.866207101,"remaining_time":1.688473091},
{"learn":[0.2537981088],"iteration":525,"passed_time":1.869744347,"remaining_time":1.684902701},
{"learn":[0.2537414269],"iteration":526,"passed_time":1.872980927,"remaining_time":1.681062577},
{"learn":[0.2536246443],"iteration":527,"passed_time":1.876566183,"remaining_time":1.677536436},
{"learn":[0.2535768367],"iteration":528,"passed_time":1.880385194,"remaining_time":1.674218197},
{"learn":[0.2535329442],"iteration":529,"passed_time":1.883897416,"remaining_time":1.670626011},
{"learn":[0.2534913819],"iteration":530,"passed_time":1.887137027,"remaining_time":1.666793344},
{"learn":[0.253445194],"iteration":531,"passed_time":1.89032561,"remaining_time":1.662918018},
{"learn":[0.2533924857],"iteration":532,"passed_time":1.894214238,"remaining_time":1.659658629},
{"learn":[0.2533780841],"iteration":533,"passed_time":1.897787429,"remaining_time":1.656121614},
{"learn":[0.2533621231],"iteration":534,"passed_time":1.907902733,"remaining_time":1.658270599},
{"learn":[0.2533483858],"iteration":535,"passed_time":1.911380826,"remaining_time":1.654628178},
{"learn":[0.2533310281],"iteration":536,"passed_time":1.915984263,"remaining_time":1.651956636},
{"learn":[0.2532746914],"iteration":537,"passed_time":1.921905876,"remaining_time":1.650409878},
{"learn":[0.2532403458],"iteration":538,"passed_time":1.925080525,"remaining_time":1.646497443},
{"learn":[0.2531647069],"iteration":539,"passed_time":1.947910887,"remaining_time":1.659331496},
{"learn":[0.2531367845],"iteration":540,"passed_time":1.951529302,"remaining_time":1.655733734},
{"learn":[0.2531060202],"iteration":541,"passed_time":1.954973474,"remaining_time":1.651988655},
{"learn":[0.2530350984],"iteration":542,"passed_time":1.962744263,"remaining_time":1.651886055},
{"learn":[0.2530210376],"iteration":543,"passed_time":1.96603941,"remaining_time":1.648003623},
{"learn":[0.2530041594],"iteration":544,"passed_time":1.984948235,"remaining_time":1.657158618},
{"learn":[0.2529909259],"iteration":545,"passed_time":1.988247453,"remaining_time":1.653231399},
{"learn":[0.2529174421],"iteration":546,"passed_time":1.991456638,"remaining_time":1.649231914},
{"learn":[0.2528940871],"iteration":547,"passed_time":1.995596211,"remaining_time":1.646002714},
{"learn":[0.2528493872],"iteration":548,"passed_time":2.002946826,"remaining_time":1.645408048},
{"learn":[0.2528007374],"iteration":549,"passed_time":2.00643535,"remaining_time":1.641628922},
{"learn":[0.2527921171],"iteration":550,"passed_time":2.010150944,"remaining_time":1.638035887},
{"learn":[0.2527429183],"iteration":551,"passed_time":2.014869562,"remaining_time":1.635256456},
{"learn":[0.2527016885],"iteration":552,"passed_time":2.018212805,"remaining_time":1.631358271},
{"learn":[0.2526822677],"iteration":553,"passed_time":2.021340642,"remaining_time":1.627288676},
{"learn":[0.2526111263],"iteration":554,"passed_time":2.024880928,"remaining_time":1.623553177},
{"learn":[0.2525607316],"iteration":555,"passed_time":2.050287967,"remaining_time":1.637280319},
{"learn":[0.2525295989],"iteration":556,"passed_time":2.053588716,"remaining_time":1.633285101},
{"learn":[0.2525158863],"iteration":557,"passed_time":2.057689067,"remaining_time":1.629925748},
{"learn":[0.252465506],"iteration":558,"passed_time":2.06111,"remaining_time":1.626027746},
{"learn":[0.2524223343],"iteration":559,"passed_time":2.064462979,"remaining_time":1.622078055},
{"learn":[0.252381046],"iteration":560,"passed_time":2.067928451,"remaining_time":1.61821852},
{"learn":[0.2523389024],"iteration":561,"passed_time":2.071485596,"remaining_time":1.614431835},
{"learn":[0.2523185675],"iteration":562,"passed_time":2.075003549,"remaining_time":1.610615543},
{"learn":[0.252306665],"iteration":563,"passed_time":2.078339617,"remaining_time":1.606659704},
{"learn":[0.2522023343],"iteration":564,"passed_time":2.084030907,"remaining_time":1.604519371},
{"learn":[0.2521926608],"iteration":565,"passed_time":2.088868752,"remaining_time":1.601712082},
{"learn":[0.2521581496],"iteration":566,"passed_time":2.09238746,"remaining_time":1.597890247},
{"learn":[0.252130421],"iteration":567,"passed_time":2.095717263,"remaining_time":1.593925806},
{"learn":[0.2521059965],"iteration":568,"passed_time":2.099129114,"remaining_time":1.590025744},
{"learn":[0.2520936147],"iteration":569,"passed_time":2.102802408,"remaining_time":1.586324623},
{"learn":[0.2520739107],"iteration":570,"passed_time":2.106884096,"remaining_time":1.582930433},
{"learn":[0.2520565344],"iteration":571,"passed_time":2.110095987,"remaining_time":1.578883011},
{"learn":[0.2519820317],"iteration":572,"passed_time":2.115740797,"remaining_time":1.576651519},
{"learn":[0.2519357323],"iteration":573,"passed_time":2.119019371,"remaining_time":1.572652007},
{"learn":[0.2518957811],"iteration":574,"passed_time":2.128015587,"remaining_time":1.572881086},
{"learn":[0.2518656464],"iteration":575,"passed_time":2.131371638,"remaining_time":1.568926345},
{"learn":[0.2518206587],"iteration":576,"passed_time":2.134602255,"remaining_time":1.564881723},
{"learn":[0.2517882894],"iteration":577,"passed_time":2.140569165,"remaining_time":1.562837695},
{"learn":[0.2517677071],"iteration":578,"passed_time":2.143722036,"remaining_time":1.558733985},
{"learn":[0.2517523928],"iteration":579,"passed_time":2.147147997,"remaining_time":1.554831308},
{"learn":[0.2517190921],"iteration":580,"passed_time":2.150472758,"remaining_time":1.55085729},
{"learn":[0.2517033798],"iteration":581,"passed_time":2.155012967,"remaining_time":1.547758454},
{"learn":[0.2516713737],"iteration":582,"passed_time":2.158095011,"remaining_time":1.543611697},
{"learn":[0.2516264987],"iteration":583,"passed_time":2.161782496,"remaining_time":1.53989986},
{"learn":[0.2515575172],"iteration":584,"passed_time":2.165304782,"remaining_time":1.536070914},
{"learn":[0.2514826633],"iteration":585,"passed_time":2.16938242,"remaining_time":1.532635361},
{"learn":[0.2514355474],"iteration":586,"passed_time":2.172619901,"remaining_time":1.528606506},
{"learn":[0.2514174675],"iteration":587,"passed_time":2.17603901,"remaining_time":1.524707606},
{"learn":[0.2513739324],"iteration":588,"passed_time":2.179195475,"remaining_time":1.520627063},
{"learn":[0.251335855],"iteration":589,"passed_time":2.191329835,"remaining_time":1.522788529},
{"learn":[0.2512769008],"iteration":590,"passed_time":2.194913879,"remaining_time":1.518984394},
{"learn":[0.2512643244],"iteration":591,"passed_time":2.198055184,"remaining_time":1.51487587},
{"learn":[0.2512483625],"iteration":592,"passed_time":2.202395868,"remaining_time":1.511593791},
{"learn":[0.2512384087],"iteration":593,"passed_time":2.205836144,"remaining_time":1.507692718},
{"learn":[0.2511924103],"iteration":594,"passed_time":2.210260408,"remaining_time":1.504462967},
{"learn":[0.2511669986],"iteration":595,"passed_time":2.213228309,"remaining_time":1.500242008},
{"learn":[0.2511121154],"iteration":596,"passed_time":2.219035147,"remaining_time":1.497941649},
{"learn":[0.2510963974],"iteration":597,"passed_time":2.222341671,"remaining_time":1.493948749},
{"learn":[0.251055169],"iteration":598,"passed_time":2.22544949,"remaining_time":1.489825118},
{"learn":[0.2510329439],"iteration":599,"passed_time":2.228653446,"remaining_time":1.485768964},
{"learn":[0.2509926331],"iteration":600,"passed_time":2.233113224,"remaining_time":1.482549378},
{"learn":[0.2509824842],"iteration":601,"passed_time":2.236500758,"remaining_time":1.47861678},
{"learn":[0.2509379942],"iteration":602,"passed_time":2.239297112,"remaining_time":1.474296772},
{"learn":[0.2509278096],"iteration":603,"passed_time":2.242161326,"remaining_time":1.4700263},
{"learn":[0.2508941842],"iteration":604,"passed_time":2.246192673,"remaining_time":1.466522489},
{"learn":[0.2508840445],"iteration":605,"passed_time":2.250542814,"remaining_time":1.463224206},
{"learn":[0.2508329818],"iteration":606,"passed_time":2.25379961,"remaining_time":1.459214574},
{"learn":[0.2507691914],"iteration":607,"passed_time":2.25709606,"remaining_time":1.455232986},
{"learn":[0.2507611342],"iteration":608,"passed_time":2.26061213,"remaining_time":1.451394652},
{"learn":[0.2507531578],"iteration":609,"passed_time":2.266043298,"remaining_time":1.448781781},
{"learn":[0.2507445006],"iteration":610,"passed_time":2.26962094,"remaining_time":1.444979617},
{"learn":[0.2507300974],"iteration":611,"passed_time":2.27271324,"remaining_time":1.440870485},
{"learn":[0.2506958367],"iteration":612,"passed_time":2.276219282,"remaining_time":1.437025876},
{"learn":[0.2506698394],"iteration":613,"passed_time":2.282933361,"remaining_time":1.435199149},
{"learn":[0.2506479193],"iteration":614,"passed_time":2.286110743,"remaining_time":1.431142498},
{"learn":[0.2505819105],"iteration":615,"passed_time":2.291708139,"remaining_time":1.428597282},
{"learn":[0.2505595145],"iteration":616,"passed_time":2.295473496,"remaining_time":1.424904942},
{"learn":[0.250548844],"iteration":617,"passed_time":2.299661667,"remaining_time":1.421473717},
{"learn":[0.2505221542],"iteration":618,"passed_time":2.303354383,"remaining_time":1.417735089},
{"learn":[0.2504815028],"iteration":619,"passed_time":2.306802987,"remaining_time":1.413846992},
{"learn":[0.2504256184],"iteration":620,"passed_time":2.310812937,"remaining_time":1.410302904},
{"learn":[0.2504120839],"iteration":621,"passed_time":2.314213216,"remaining_time":1.406386809},
{"learn":[0.2503676065],"iteration":622,"passed_time":2.317460343,"remaining_time":1.402379694},
{"learn":[0.2503144933],"iteration":623,"passed_time":2.320802645,"remaining_time":1.398432363},
{"learn":[0.2503019433],"iteration":624,"passed_time":2.324080534,"remaining_time":1.39444832},
{"learn":[0.2502824703],"iteration":625,"passed_time":2.327390279,"remaining_time":1.390485566},
{"learn":[0.2502532133],"iteration":626,"passed_time":2.330774702,"remaining_time":1.38656932},
{"learn":[0.2501891769],"iteration":627,"passed_time":2.333856882,"remaining_time":1.382475733},
{"learn":[0.2501680735],"iteration":628,"passed_time":2.336602718,"remaining_time":1.378186977},
{"learn":[0.2501571177],"iteration":629,"passed_time":2.340237878,"remaining_time":1.37442542},
{"learn":[0.250148126],"iteration":630,"passed_time":2.343674938,"remaining_time":1.370548418},
{"learn":[0.2501126346],"iteration":631,"passed_time":2.346896946,"remaining_time":1.366547589},
{"learn":[0.2500545044],"iteration":632,"passed_time":2.3500661,"remaining_time":1.362518576},
{"learn":[0.2500139491],"iteration":633,"passed_time":2.353338063,"remaining_time":1.358551626},
{"learn":[0.2500033982],"iteration":634,"passed_time":2.358068404,"remaining_time":1.355425146},
{"learn":[0.2499726376],"iteration":635,"passed_time":2.362340129,"remaining_time":1.352031143},
{"learn":[0.2499620995],"iteration":636,"passed_time":2.365410794,"remaining_time":1.34794995},
{"learn":[0.2499531192],"iteration":637,"passed_time":2.369136092,"remaining_time":1.344243363},
{"learn":[0.2499067816],"iteration":638,"passed_time":2.372639049,"remaining_time":1.340411106},
{"learn":[0.2498712535],"iteration":639,"passed_time":2.378454009,"remaining_time":1.33788038},
{"learn":[0.2498419435],"iteration":640,"passed_time":2.381901029,"remaining_time":1.334013213},
{"learn":[0.2498170188],"iteration":641,"passed_time":2.385010633,"remaining_time":1.3299592},
{"learn":[0.2498094502],"iteration":642,"passed_time":2.38849361,"remaining_time":1.326115426},
{"learn":[0.2497973727],"iteration":643,"passed_time":2.391792369,"remaining_time":1.322170937},
{"learn":[0.2497694063],"iteration":644,"passed_time":2.396006759,"remaining_time":1.318732402},
{"learn":[0.2497398042],"iteration":645,"passed_time":2.399320714,"remaining_time":1.314798039},
{"learn":[0.249668474],"iteration":646,"passed_time":2.403089983,"remaining_time":1.311114009},
{"learn":[0.249627136],"iteration":647,"passed_time":2.406432205,"remaining_time":1.307197741},
{"learn":[0.2495945375],"iteration":648,"passed_time":2.409841952,"remaining_time":1.303319761},
{"learn":[0.2495457343],"iteration":649,"passed_time":2.413290625,"remaining_time":1.299464182},
{"learn":[0.2495274158],"iteration":650,"passed_time":2.416990082,"remaining_time":1.295744299},
{"learn":[0.2495047077],"iteration":651,"passed_time":2.420424263,"remaining_time":1.291882889},
{"learn":[0.2494443544],"iteration":652,"passed_time":2.424009717,"remaining_time":1.288103173},
{"learn":[0.2494246335],"iteration":653,"passed_time":2.427991034,"remaining_time":1.284533483},
{"learn":[0.2494156979],"iteration":654,"passed_time":2.432024561,"remaining_time":1.280990036},
{"learn":[0.2493938538],"iteration":655,"passed_time":2.435622721,"remaining_time":1.277216793},
{"learn":[0.249388088],"iteration":656,"passed_time":2.439015246,"remaining_time":1.273336727},
{"learn":[0.2493054203],"iteration":657,"passed_time":2.442191156,"remaining_time":1.269345555},
{"learn":[0.2492662481],"iteration":658,"passed_time":2.445555379,"remaining_time":1.265454301},
{"learn":[0.2492211678],"iteration":659,"passed_time":2.448717798,"remaining_time":1.261460684},
{"learn":[0.2492072343],"iteration":660,"passed_time":2.452424313,"remaining_time":1.257748627},
{"learn":[0.2491740972],"iteration":661,"passed_time":2.45588288,"remaining_time":1.25390999},
{"learn":[0.2491466596],"iteration":662,"passed_time":2.460132649,"remaining_time":1.250474665},
{"learn":[0.2491371983],"iteration":663,"passed_time":2.463322977,"remaining_time":1.246500783},
{"learn":[0.2491294477],"iteration":664,"passed_time":2.467234613,"remaining_time":1.242892624},
{"learn":[0.2490794975],"iteration":665,"passed_time":2.472602527,"remaining_time":1.24001388},
{"learn":[0.249066823],"iteration":666,"passed_time":2.475942563,"remaining_time":1.236115253},
{"learn":[0.2490590565],"iteration":667,"passed_time":2.47901623,"remaining_time":1.232085911},
{"learn":[0.249025731],"iteration":668,"passed_time":2.482720217,"remaining_time":1.228371288},
{"learn":[0.2490180281],"iteration":669,"passed_time":2.485912194,"remaining_time":1.224404513},
{"learn":[0.2490018394],"iteration":670,"passed_time":2.489034869,"remaining_time":1.220406068},
{"learn":[0.2489704984],"iteration":671,"passed_time":2.492662447,"remaining_time":1.216656671},
{"learn":[0.2489495993],"iteration":672,"passed_time":2.495985183,"remaining_time":1.212759517},
{"learn":[0.2488901224],"iteration":673,"passed_time":2.499404173,"remaining_time":1.208910624},
{"learn":[0.2488329912],"iteration":674,"passed_time":2.502807638,"remaining_time":1.20505553},
{"learn":[0.2487964524],"iteration":675,"passed_time":2.5073343,"remaining_time":1.201740108},
{"learn":[0.248773612],"iteration":676,"passed_time":2.510654032,"remaining_time":1.197845276},
{"learn":[0.2487507482],"iteration":677,"passed_time":2.514075047,"remaining_time":1.194000243},
{"learn":[0.2487180928],"iteration":678,"passed_time":2.517288735,"remaining_time":1.190058445},
{"learn":[0.2486870168],"iteration":679,"passed_time":2.520420773,"remaining_time":1.186080364},
{"learn":[0.2486576904],"iteration":680,"passed_time":2.525934362,"remaining_time":1.183220354},
{"learn":[0.2486415844],"iteration":681,"passed_time":2.529303248,"remaining_time":1.179352541},
{"learn":[0.2486121413],"iteration":682,"passed_time":2.533339532,"remaining_time":1.175795947},
{"learn":[0.2485914002],"iteration":683,"passed_time":2.536653378,"remaining_time":1.171904192},
{"learn":[0.2485618303],"iteration":684,"passed_time":2.540815974,"remaining_time":1.168404426},
{"learn":[0.248510384],"iteration":685,"passed_time":2.544226523,"remaining_time":1.164558496},
{"learn":[0.2484840056],"iteration":686,"passed_time":2.547450467,"remaining_time":1.160628815},
{"learn":[0.2484121032],"iteration":687,"passed_time":2.554347268,"remaining_time":1.158366784},
{"learn":[0.2483599145],"iteration":688,"passed_time":2.557663037,"remaining_time":1.154474898},
{"learn":[0.2483323584],"iteration":689,"passed_time":2.561262268,"remaining_time":1.150712033},
{"learn":[0.2482880951],"iteration":690,"passed_time":2.56445965,"remaining_time":1.146769945},
{"learn":[0.2482612728],"iteration":691,"passed_time":2.567516445,"remaining_time":1.142767435},
{"learn":[0.2482202999],"iteration":692,"passed_time":2.57110161,"remaining_time":1.139001723},
{"learn":[0.2481874839],"iteration":693,"passed_time":2.574364609,"remaining_time":1.135094482},
{"learn":[0.2481551118],"iteration":694,"passed_time":2.577836547,"remaining_time":1.131280787},
{"learn":[0.2481351488],"iteration":695,"passed_time":2.581141776,"remaining_time":1.127395258},
{"learn":[0.2480927996],"iteration":696,"passed_time":2.584414095,"remaining_time":1.123497089},
{"learn":[0.2480831738],"iteration":697,"passed_time":2.587858848,"remaining_time":1.119675318},
{"learn":[0.2480530174],"iteration":698,"passed_time":2.591315902,"remaining_time":1.115859923},
{"learn":[0.24802821],"iteration":699,"passed_time":2.5958617,"remaining_time":1.112512157},
{"learn":[0.2480180737],"iteration":700,"passed_time":2.600072424,"remaining_time":1.109018052},
{"learn":[0.2479844922],"iteration":701,"passed_time":2.603356415,"remaining_time":1.105128507},
{"learn":[0.2479537514],"iteration":702,"passed_time":2.606642172,"remaining_time":1.10124143},
{"learn":[0.2479469162],"iteration":703,"passed_time":2.610459035,"remaining_time":1.097579367},
{"learn":[0.2479297272],"iteration":704,"passed_time":2.614092077,"remaining_time":1.093839947},
{"learn":[0.2479198163],"iteration":705,"passed_time":2.617305507,"remaining_time":1.089926089},
{"learn":[0.2479057436],"iteration":706,"passed_time":2.620624732,"remaining_time":1.086058057},
{"learn":[0.2478957794],"iteration":707,"passed_time":2.624372067,"remaining_time":1.082368141},
{"learn":[0.2478693951],"iteration":708,"passed_time":2.628046321,"remaining_time":1.078648067},
{"learn":[0.2478590626],"iteration":709,"passed_time":2.631121832,"remaining_time":1.074683565},
{"learn":[0.247794462],"iteration":710,"passed_time":2.634337249,"remaining_time":1.070778432},
{"learn":[0.2477871592],"iteration":711,"passed_time":2.637490554,"remaining_time":1.066850112},
{"learn":[0.2477395669],"iteration":712,"passed_time":2.64339907,"remaining_time":1.064033006},
{"learn":[0.2477271127],"iteration":713,"passed_time":2.646657779,"remaining_time":1.060145833},
{"learn":[0.2476995111],"iteration":714,"passed_time":2.649781566,"remaining_time":1.056206638},
{"learn":[0.2476858182],"iteration":715,"passed_time":2.653291139,"remaining_time":1.052422742},
{"learn":[0.2476592984],"iteration":716,"passed_time":2.657486567,"remaining_time":1.048910319},
{"learn":[0.2476145553],"iteration":717,"passed_time":2.660668368,"remaining_time":1.044997883},
{"learn":[0.2475769676],"iteration":718,"passed_time":2.66414401,"remaining_time":1.041202318},
{"learn":[0.2475638784],"iteration":719,"passed_time":2.667374531,"remaining_time":1.037312318},
{"learn":[0.247535587],"iteration":720,"passed_time":2.671336999,"remaining_time":1.033707382},
{"learn":[0.24749509],"iteration":721,"passed_time":2.674846692,"remaining_time":1.029927119},
{"learn":[0.2474801383],"iteration":722,"passed_time":2.678000909,"remaining_time":1.026011413},
{"learn":[0.2474549087],"iteration":723,"passed_time":2.682066662,"remaining_time":1.022445302},
{"learn":[0.247441958],"iteration":724,"passed_time":2.685104598,"remaining_time":1.018487951},
{"learn":[0.2474208233],"iteration":725,"passed_time":2.689213754,"remaining_time":1.014937422},
{"learn":[0.2473965269],"iteration":726,"passed_time":2.693106114,"remaining_time":1.011303947},
{"learn":[0.2473583593],"iteration":727,"passed_time":2.696179427,"remaining_time":1.007363742},
{"learn":[0.2473432035],"iteration":728,"passed_time":2.699323584,"remaining_time":1.003452251},
{"learn":[0.2473334665],"iteration":729,"passed_time":2.702735599,"remaining_time":0.9996419338},
{"learn":[0.2473232407],"iteration":730,"passed_time":2.705766311,"remaining_time":0.9956923909},
{"learn":[0.2473161814],"iteration":731,"passed_time":2.708944202,"remaining_time":0.9917992433},
{"learn":[0.2473003853],"iteration":732,"passed_time":2.712452031,"remaining_time":0.9880282296},
{"learn":[0.2472849421],"iteration":733,"passed_time":2.716325106,"remaining_time":0.9843902974},
{"learn":[0.2472744428],"iteration":734,"passed_time":2.721603296,"remaining_time":0.9812583312},
{"learn":[0.2472310949],"iteration":735,"passed_time":2.726069042,"remaining_time":0.9778291129},
{"learn":[0.2472222646],"iteration":736,"passed_time":2.729366545,"remaining_time":0.9739801919},
{"learn":[0.2472036634],"iteration":737,"passed_time":2.732946177,"remaining_time":0.9702329246},
{"learn":[0.2471986888],"iteration":738,"passed_time":2.737411895,"remaining_time":0.966799059},
{"learn":[0.2471721156],"iteration":739,"passed_time":2.740714621,"remaining_time":0.9629537859},
{"learn":[0.2471174784],"iteration":740,"passed_time":2.743833808,"remaining_time":0.9590458249},
{"learn":[0.2471098404],"iteration":741,"passed_time":2.747080556,"remaining_time":0.9551843442},
{"learn":[0.2471029622],"iteration":742,"passed_time":2.750741777,"remaining_time":0.9514678825},
{"learn":[0.2470935125],"iteration":743,"passed_time":2.756606193,"remaining_time":0.9485096579},
{"learn":[0.2470877865],"iteration":744,"passed_time":2.760281947,"remaining_time":0.9447944918},
{"learn":[0.2470717014],"iteration":745,"passed_time":2.763426061,"remaining_time":0.9408984175},
{"learn":[0.247043408],"iteration":746,"passed_time":2.767182194,"remaining_time":0.9372116398},
{"learn":[0.2470200139],"iteration":747,"passed_time":2.770380438,"remaining_time":0.9333367252},
{"learn":[0.2470091954],"iteration":748,"passed_time":2.773536593,"remaining_time":0.9294495126},
{"learn":[0.2469998023],"iteration":749,"passed_time":2.776957304,"remaining_time":0.9256524347},
{"learn":[0.246976641],"iteration":750,"passed_time":2.780017409,"remaining_time":0.9217367972},
{"learn":[0.2469686202],"iteration":751,"passed_time":2.783581499,"remaining_time":0.9179896434},
{"learn":[0.2469470245],"iteration":752,"passed_time":2.786721801,"remaining_time":0.9141039639},
{"learn":[0.2469340263],"iteration":753,"passed_time":2.789853911,"remaining_time":0.9102175889},
{"learn":[0.2469249514],"iteration":754,"passed_time":2.793648092,"remaining_time":0.9065480565},
{"learn":[0.246915897],"iteration":755,"passed_time":2.797939199,"remaining_time":0.9030385774},
{"learn":[0.2468870041],"iteration":756,"passed_time":2.801211085,"remaining_time":0.8991998595},
{"learn":[0.2468737158],"iteration":757,"passed_time":2.804736139,"remaining_time":0.8954434639},
{"learn":[0.2468568028],"iteration":758,"passed_time":2.807892477,"remaining_time":0.8915706022},
{"learn":[0.2468364738],"iteration":759,"passed_time":2.812344276,"remaining_time":0.8881087186},
{"learn":[0.2468002136],"iteration":760,"passed_time":2.815371009,"remaining_time":0.884196677},
{"learn":[0.2467890684],"iteration":761,"passed_time":2.818861579,"remaining_time":0.8804318318},
{"learn":[0.2467675678],"iteration":762,"passed_time":2.822071718,"remaining_time":0.876580599},
{"learn":[0.246758887],"iteration":763,"passed_time":2.826538966,"remaining_time":0.8731193664},
{"learn":[0.2467380142],"iteration":764,"passed_time":2.830683879,"remaining_time":0.8695564857},
{"learn":[0.2467015813],"iteration":765,"passed_time":2.835617334,"remaining_time":0.8662329716},
{"learn":[0.2466937219],"iteration":766,"passed_time":2.838818731,"remaining_time":0.8623790929},
{"learn":[0.2466648313],"iteration":767,"passed_time":2.842197157,"remaining_time":0.8585803912},
{"learn":[0.2466573387],"iteration":768,"passed_time":2.845577843,"remaining_time":0.8547834613},
{"learn":[0.246648936],"iteration":769,"passed_time":2.849772867,"remaining_time":0.8512308565},
{"learn":[0.2466357397],"iteration":770,"passed_time":2.853015777,"remaining_time":0.847393791},
{"learn":[0.2466273564],"iteration":771,"passed_time":2.856850973,"remaining_time":0.8437331888},
{"learn":[0.2465937298],"iteration":772,"passed_time":2.861922169,"remaining_time":0.8404351001},
{"learn":[0.2465740585],"iteration":773,"passed_time":2.865492003,"remaining_time":0.8366940474},
{"learn":[0.24654746],"iteration":774,"passed_time":2.869018636,"remaining_time":0.8329408945},
{"learn":[0.2465364497],"iteration":775,"passed_time":2.872402332,"remaining_time":0.829147065},
{"learn":[0.246511112],"iteration":776,"passed_time":2.876320208,"remaining_time":0.8255076016},
{"learn":[0.2465051032],"iteration":777,"passed_time":2.879862963,"remaining_time":0.8217603828},
{"learn":[0.2464987769],"iteration":778,"passed_time":2.882990077,"remaining_time":0.8178957727},
{"learn":[0.2464756259],"iteration":779,"passed_time":2.88637724,"remaining_time":0.814106401},
{"learn":[0.246453105],"iteration":780,"passed_time":2.889945223,"remaining_time":0.810368763},
{"learn":[0.2464329589],"iteration":781,"passed_time":2.893781385,"remaining_time":0.8067063195},
{"learn":[0.2464268138],"iteration":782,"passed_time":2.897155312,"remaining_time":0.8029153292},
{"learn":[0.2464052328],"iteration":783,"passed_time":2.900266311,"remaining_time":0.7990529632},
{"learn":[0.2463886539],"iteration":784,"passed_time":2.903359219,"remaining_time":0.7951875567},
{"learn":[0.2463753582],"iteration":785,"passed_time":2.906458133,"remaining_time":0.7913257512},
{"learn":[0.2463542293],"iteration":786,"passed_time":2.911309285,"remaining_time":0.7879401241},
{"learn":[0.2463521785],"iteration":787,"passed_time":2.914501302,"remaining_time":0.7841044113},
{"learn":[0.2463256208],"iteration":788,"passed_time":2.917488085,"remaining_time":0.7802154449},
{"learn":[0.2463064915],"iteration":789,"passed_time":2.920655434,"remaining_time":0.776376761},
{"learn":[0.2462808109],"iteration":790,"passed_time":2.925134382,"remaining_time":0.7728863286},
{"learn":[0.246274726],"iteration":791,"passed_time":2.928439132,"remaining_time":0.7690850245},
{"learn":[0.2462526008],"iteration":792,"passed_time":2.931589466,"remaining_time":0.765244665},
{"learn":[0.2462282186],"iteration":793,"passed_time":2.934878134,"remaining_time":0.761441934},
{"learn":[0.2462187277],"iteration":794,"passed_time":2.938290384,"remaining_time":0.7576723631},
{"learn":[0.2462102706],"iteration":795,"passed_time":2.94137867,"remaining_time":0.7538206643},
{"learn":[0.2462037213],"iteration":796,"passed_time":2.947555729,"remaining_time":0.7507576072},
{"learn":[0.2461924314],"iteration":797,"passed_time":2.950758748,"remaining_time":0.7469339186},
{"learn":[0.2461844234],"iteration":798,"passed_time":2.955236164,"remaining_time":0.7434323766},
{"learn":[0.2461627451],"iteration":799,"passed_time":2.959634247,"remaining_time":0.7399085617},
{"learn":[0.2461483586],"iteration":800,"passed_time":2.962573341,"remaining_time":0.7360200934},
{"learn":[0.2461280829],"iteration":801,"passed_time":2.965659046,"remaining_time":0.7321701884},
{"learn":[0.2461196625],"iteration":802,"passed_time":2.969566648,"remaining_time":0.7285238228},
{"learn":[0.2461130558],"iteration":803,"passed_time":2.972696329,"remaining_time":0.7246871648},
{"learn":[0.2461013268],"iteration":804,"passed_time":2.975783277,"remaining_time":0.7208419118},
{"learn":[0.2460933643],"iteration":805,"passed_time":2.978877629,"remaining_time":0.7170003227},
{"learn":[0.2460787341],"iteration":806,"passed_time":2.986662774,"remaining_time":0.7142824231},
{"learn":[0.2460634386],"iteration":807,"passed_time":2.990011922,"remaining_time":0.7104978824},
{"learn":[0.2460479643],"iteration":808,"passed_time":2.994201736,"remaining_time":0.7069128945},
{"learn":[0.2460084848],"iteration":809,"passed_time":2.997868523,"remaining_time":0.7032037276},
{"learn":[0.2460002515],"iteration":810,"passed_time":3.003634234,"remaining_time":0.6999838104},
{"learn":[0.2459828498],"iteration":811,"passed_time":3.006900288,"remaining_time":0.6961788843},
{"learn":[0.2459585743],"iteration":812,"passed_time":3.010905177,"remaining_time":0.6925452253},
{"learn":[0.2459364565],"iteration":813,"passed_time":3.014354871,"remaining_time":0.6887837912},
{"learn":[0.2459260955],"iteration":814,"passed_time":3.017948697,"remaining_time":0.6850558392},
{"learn":[0.2459124757],"iteration":815,"passed_time":3.021145127,"remaining_time":0.6812386071},
{"learn":[0.2459054716],"iteration":816,"passed_time":3.024258371,"remaining_time":0.6774042618},
{"learn":[0.2458839144],"iteration":817,"passed_time":3.028862439,"remaining_time":0.6739033788},
{"learn":[0.2458644473],"iteration":818,"passed_time":3.031931252,"remaining_time":0.6700605088},
{"learn":[0.2458484847],"iteration":819,"passed_time":3.037599183,"remaining_time":0.6667900645},
{"learn":[0.2458103781],"iteration":820,"passed_time":3.041095178,"remaining_time":0.6630402399},
{"learn":[0.2458010636],"iteration":821,"passed_time":3.044232378,"remaining_time":0.6592133372},
{"learn":[0.24579204],"iteration":822,"passed_time":3.047343091,"remaining_time":0.6553824145},
{"learn":[0.2457687621],"iteration":823,"passed_time":3.050845804,"remaining_time":0.6516369678},
{"learn":[0.2457326609],"iteration":824,"passed_time":3.055612987,"remaining_time":0.6481603306},
{"learn":[0.2457038276],"iteration":825,"passed_time":3.05877135,"remaining_time":0.6443416646},
{"learn":[0.2456618593],"iteration":826,"passed_time":3.06285971,"remaining_time":0.6407191413},
{"learn":[0.2456447959],"iteration":827,"passed_time":3.066385628,"remaining_time":0.6369786571},
{"learn":[0.2456203683],"iteration":828,"passed_time":3.069543544,"remaining_time":0.6331627818},
{"learn":[0.2456140453],"iteration":829,"passed_time":3.072780878,"remaining_time":0.6293647581},
{"learn":[0.2455996828],"iteration":830,"passed_time":3.075965049,"remaining_time":0.6255572723},
{"learn":[0.2455950038],"iteration":831,"passed_time":3.079231224,"remaining_time":0.6217678433},
{"learn":[0.2455605064],"iteration":832,"passed_time":3.08251229,"remaining_time":0.617982656},
{"learn":[0.2455491393],"iteration":833,"passed_time":3.085808556,"remaining_time":0.6142017029},
{"learn":[0.2455396542],"iteration":834,"passed_time":3.088936501,"remaining_time":0.6103886498},
{"learn":[0.2455222626],"iteration":835,"passed_time":3.092152902,"remaining_time":0.6065945885},
{"learn":[0.245514624],"iteration":836,"passed_time":3.096550057,"remaining_time":0.6030318509},
{"learn":[0.2455068062],"iteration":837,"passed_time":3.10013665,"remaining_time":0.5993104263},
{"learn":[0.2454890971],"iteration":838,"passed_time":3.106688073,"remaining_time":0.5961582595},
{"learn":[0.2454738942],"iteration":839,"passed_time":3.109841743,"remaining_time":0.5923508082},
{"learn":[0.2454616915],"iteration":840,"passed_time":3.114354013,"remaining_time":0.5888017694},
{"learn":[0.2454397971],"iteration":841,"passed_time":3.117481635,"remaining_time":0.5849906156},
{"learn":[0.245428971],"iteration":842,"passed_time":3.120565431,"remaining_time":0.5811729213},
{"learn":[0.2453954615],"iteration":843,"passed_time":3.123677441,"remaining_time":0.577362181},
{"learn":[0.2453887524],"iteration":844,"passed_time":3.126962651,"remaining_time":0.5735848649},
{"learn":[0.2453555749],"iteration":845,"passed_time":3.131028541,"remaining_time":0.569950822},
{"learn":[0.2453364523],"iteration":846,"passed_time":3.134168605,"remaining_time":0.5661485202},
{"learn":[0.2453284161],"iteration":847,"passed_time":3.13814271,"remaining_time":0.5624972783},
{"learn":[0.2453229285],"iteration":848,"passed_time":3.14439721,"remaining_time":0.5592508582},
{"learn":[0.2453178416],"iteration":849,"passed_time":3.153213379,"remaining_time":0.5564494198},
{"learn":[0.2452900063],"iteration":850,"passed_time":3.156324384,"remaining_time":0.5526349392},
{"learn":[0.2452731709],"iteration":851,"passed_time":3.160046829,"remaining_time":0.5489283225},
{"learn":[0.2452617589],"iteration":852,"passed_time":3.163679896,"remaining_time":0.5452062657},
{"learn":[0.2452569174],"iteration":853,"passed_time":3.166835039,"remaining_time":0.5414027115},
{"learn":[0.2452419329],"iteration":854,"passed_time":3.170001536,"remaining_time":0.5376025998},
{"learn":[0.2452114238],"iteration":855,"passed_time":3.173341168,"remaining_time":0.5338330937},
{"learn":[0.2451925344],"iteration":856,"passed_time":3.178525517,"remaining_time":0.5303724025},
{"learn":[0.2451871171],"iteration":857,"passed_time":3.181561196,"remaining_time":0.5265520861},
{"learn":[0.2451750214],"iteration":858,"passed_time":3.184822471,"remaining_time":0.5227706267},
{"learn":[0.2451631257],"iteration":859,"passed_time":3.188351557,"remaining_time":0.5190339744},
{"learn":[0.2451321219],"iteration":860,"passed_time":3.192556612,"remaining_time":0.5154069327},
{"learn":[0.2451063734],"iteration":861,"passed_time":3.195833562,"remaining_time":0.511629967},
{"learn":[0.2450967029],"iteration":862,"passed_time":3.201081087,"remaining_time":0.508166986},
{"learn":[0.2450704909],"iteration":863,"passed_time":3.207114679,"remaining_time":0.5048236069},
{"learn":[0.2450552785],"iteration":864,"passed_time":3.21055913,"remaining_time":0.501069922},
{"learn":[0.2450442233],"iteration":865,"passed_time":3.213839306,"remaining_time":0.4972915323},
{"learn":[0.24501186],"iteration":866,"passed_time":3.2176064,"remaining_time":0.4935889864},
{"learn":[0.2450064726],"iteration":867,"passed_time":3.22076615,"remaining_time":0.4897939307},
{"learn":[0.2449891797],"iteration":868,"passed_time":3.226524985,"remaining_time":0.4863921439},
{"learn":[0.2449749292],"iteration":869,"passed_time":3.22959468,"remaining_time":0.4825831132},
{"learn":[0.2449693543],"iteration":870,"passed_time":3.23291407,"remaining_time":0.4788127612},
{"learn":[0.2449647263],"iteration":871,"passed_time":3.235919486,"remaining_time":0.4749973558},
{"learn":[0.2449425053],"iteration":872,"passed_time":3.241914097,"remaining_time":0.4716186602},
{"learn":[0.2449294712],"iteration":873,"passed_time":3.245281283,"remaining_time":0.4678551963},
{"learn":[0.2449262828],"iteration":874,"passed_time":3.249152361,"remaining_time":0.464164623},
{"learn":[0.2449049154],"iteration":875,"passed_time":3.252217974,"remaining_time":0.4603596219},
{"learn":[0.2448882741],"iteration":876,"passed_time":3.256025961,"remaining_time":0.4566604256},
{"learn":[0.2448704457],"iteration":877,"passed_time":3.259511006,"remaining_time":0.4529161079},
{"learn":[0.244861688],"iteration":878,"passed_time":3.262847574,"remaining_time":0.4491519414},
{"learn":[0.2448537237],"iteration":879,"passed_time":3.266093925,"remaining_time":0.4453764443},
{"learn":[0.2448304874],"iteration":880,"passed_time":3.269615248,"remaining_time":0.44163929},
{"learn":[0.2448257138],"iteration":881,"passed_time":3.272646243,"remaining_time":0.4378370257},
{"learn":[0.2448082306],"iteration":882,"passed_time":3.276086676,"remaining_time":0.43409076},
{"learn":[0.2447876004],"iteration":883,"passed_time":3.280691032,"remaining_time":0.4304979182},
{"learn":[0.2447792904],"iteration":884,"passed_time":3.283589363,"remaining_time":0.4266811036},
{"learn":[0.244764718],"iteration":885,"passed_time":3.28713298,"remaining_time":0.4229493902},
{"learn":[0.2447497547],"iteration":886,"passed_time":3.290257659,"remaining_time":0.4191647299},
{"learn":[0.2447323372],"iteration":887,"passed_time":3.295403851,"remaining_time":0.4156365217},
{"learn":[0.2447282785],"iteration":888,"passed_time":3.298843457,"remaining_time":0.4118915903},
{"learn":[0.2447205334],"iteration":889,"passed_time":3.302674187,"remaining_time":0.408195686},
{"learn":[0.2447133593],"iteration":890,"passed_time":3.306238758,"remaining_time":0.4044669188},
{"learn":[0.2447051389],"iteration":891,"passed_time":3.310434521,"remaining_time":0.400814942},
{"learn":[0.2446982756],"iteration":892,"passed_time":3.321200823,"remaining_time":0.3979490347},
{"learn":[0.2446914744],"iteration":893,"passed_time":3.324664365,"remaining_time":0.394199578},
{"learn":[0.2446781048],"iteration":894,"passed_time":3.328099652,"remaining_time":0.3904474452},
{"learn":[0.2446523876],"iteration":895,"passed_time":3.331461513,"remaining_time":0.3866874971},
{"learn":[0.2446420225],"iteration":896,"passed_time":3.336797053,"remaining_time":0.3831550685},
{"learn":[0.2446271872],"iteration":897,"passed_time":3.340096206,"remaining_time":0.3793873197},
{"learn":[0.2446109937],"iteration":898,"passed_time":3.343403095,"remaining_time":0.3756214823},
{"learn":[0.2445969337],"iteration":899,"passed_time":3.347235562,"remaining_time":0.3719150624},
{"learn":[0.2445919297],"iteration":900,"passed_time":3.351371263,"remaining_time":0.3682416815},
{"learn":[0.2445765482],"iteration":901,"passed_time":3.354979459,"remaining_time":0.3645099634},
{"learn":[0.2445608735],"iteration":902,"passed_time":3.358499619,"remaining_time":0.3607690621},
{"learn":[0.244543949],"iteration":903,"passed_time":3.361583678,"remaining_time":0.3569823375},
{"learn":[0.2445357366],"iteration":904,"passed_time":3.365107416,"remaining_time":0.35324332},
{"learn":[0.2445211516],"iteration":905,"passed_time":3.369298496,"remaining_time":0.3495740162},
{"learn":[0.2445116175],"iteration":906,"passed_time":3.372860283,"remaining_time":0.3458390367},
{"learn":[0.2444968634],"iteration":907,"passed_time":3.380139298,"remaining_time":0.3424810742},
{"learn":[0.244490297],"iteration":908,"passed_time":3.383279215,"remaining_time":0.3387001194},
{"learn":[0.2444797675],"iteration":909,"passed_time":3.387428362,"remaining_time":0.3350203875},
{"learn":[0.244473801],"iteration":910,"passed_time":3.390531323,"remaining_time":0.331237418},
{"learn":[0.2444508043],"iteration":911,"passed_time":3.393575566,"remaining_time":0.3274502739},
{"learn":[0.2444280975],"iteration":912,"passed_time":3.397331978,"remaining_time":0.32373262},
{"learn":[0.2444244796],"iteration":913,"passed_time":3.400530064,"remaining_time":0.3199623474},
{"learn":[0.2444188459],"iteration":914,"passed_time":3.40404507,"remaining_time":0.316222766},
{"learn":[0.2444150281],"iteration":915,"passed_time":3.407129449,"remaining_time":0.3124441853},
{"learn":[0.2444070202],"iteration":916,"passed_time":3.41107357,"remaining_time":0.308744936},
{"learn":[0.2444017078],"iteration":917,"passed_time":3.414169389,"remaining_time":0.304969379},
{"learn":[0.2443955569],"iteration":918,"passed_time":3.418502763,"remaining_time":0.3013043784},
{"learn":[0.24438988],"iteration":919,"passed_time":3.421643144,"remaining_time":0.2975341864},
{"learn":[0.2443756865],"iteration":920,"passed_time":3.425106864,"remaining_time":0.2937930969},
{"learn":[0.2443681257],"iteration":921,"passed_time":3.428901882,"remaining_time":0.2900806364},
{"learn":[0.2443644747],"iteration":922,"passed_time":3.432104521,"remaining_time":0.2863185786},
{"learn":[0.244361077],"iteration":923,"passed_time":3.435254756,"remaining_time":0.2825534215},
{"learn":[0.2443564672],"iteration":924,"passed_time":3.438745228,"remaining_time":0.2788171806},
{"learn":[0.2443514414],"iteration":925,"passed_time":3.442321351,"remaining_time":0.2750883153},
{"learn":[0.2443433806],"iteration":926,"passed_time":3.445939359,"remaining_time":0.2713630779},
{"learn":[0.2443297468],"iteration":927,"passed_time":3.450671379,"remaining_time":0.2677245035},
{"learn":[0.2443152136],"iteration":928,"passed_time":3.457478773,"remaining_time":0.2642421882},
{"learn":[0.2442971696],"iteration":929,"passed_time":3.461015777,"remaining_time":0.2605065639},
{"learn":[0.2442894272],"iteration":930,"passed_time":3.464278948,"remaining_time":0.2567510713},
{"learn":[0.2442844648],"iteration":931,"passed_time":3.467713459,"remaining_time":0.2530091365},
{"learn":[0.2442809346],"iteration":932,"passed_time":3.471052108,"remaining_time":0.2492609766},
{"learn":[0.2442742136],"iteration":933,"passed_time":3.47438298,"remaining_time":0.2455131442},
{"learn":[0.2442460772],"iteration":934,"passed_time":3.479053454,"remaining_time":0.241859331},
{"learn":[0.244235268],"iteration":935,"passed_time":3.482926516,"remaining_time":0.2381488216},
{"learn":[0.2442320504],"iteration":936,"passed_time":3.487417464,"remaining_time":0.2344795093},
{"learn":[0.2442281521],"iteration":937,"passed_time":3.491574994,"remaining_time":0.2307864069},
{"learn":[0.2442213836],"iteration":938,"passed_time":3.49493281,"remaining_time":0.2270403636},
{"learn":[0.2442144493],"iteration":939,"passed_time":3.498460504,"remaining_time":0.2233059896},
{"learn":[0.2442097631],"iteration":940,"passed_time":3.501539194,"remaining_time":0.2195439027},
{"learn":[0.2441959359],"iteration":941,"passed_time":3.504652631,"remaining_time":0.2157854062},
{"learn":[0.2441646487],"iteration":942,"passed_time":3.509367595,"remaining_time":0.2121250826},
{"learn":[0.2441509588],"iteration":943,"passed_time":3.512750908,"remaining_time":0.2083835285},
{"learn":[0.2441380494],"iteration":944,"passed_time":3.515897102,"remaining_time":0.2046289318},
{"learn":[0.2441352672],"iteration":945,"passed_time":3.518878874,"remaining_time":0.2008662359},
{"learn":[0.2441304687],"iteration":946,"passed_time":3.522403932,"remaining_time":0.1971355949},
{"learn":[0.2441261646],"iteration":947,"passed_time":3.525550272,"remaining_time":0.1933846141},
{"learn":[0.2441124634],"iteration":948,"passed_time":3.528951639,"remaining_time":0.1896486128},
{"learn":[0.2441019795],"iteration":949,"passed_time":3.531958978,"remaining_time":0.1858925778},
{"learn":[0.2440943526],"iteration":950,"passed_time":3.534986046,"remaining_time":0.1821391338},
{"learn":[0.2440824499],"iteration":951,"passed_time":3.53836755,"remaining_time":0.1784050865},
{"learn":[0.2440779334],"iteration":952,"passed_time":3.54170554,"remaining_time":0.1746696331},
{"learn":[0.2440677779],"iteration":953,"passed_time":3.549572425,"remaining_time":0.1711533874},
{"learn":[0.2440604137],"iteration":954,"passed_time":3.553562844,"remaining_time":0.1674453696},
{"learn":[0.2440565104],"iteration":955,"passed_time":3.562178253,"remaining_time":0.1639496267},
{"learn":[0.2440517557],"iteration":956,"passed_time":3.56537887,"remaining_time":0.1601998865},
{"learn":[0.2440474306],"iteration":957,"passed_time":3.569156948,"remaining_time":0.1564766094},
{"learn":[0.24404178],"iteration":958,"passed_time":3.572393194,"remaining_time":0.1527300531},
{"learn":[0.2440350597],"iteration":959,"passed_time":3.575586067,"remaining_time":0.1489827528},
{"learn":[0.2440216107],"iteration":960,"passed_time":3.578943634,"remaining_time":0.14524329},
{"learn":[0.2440172038],"iteration":961,"passed_time":3.582137407,"remaining_time":0.1414981512},
{"learn":[0.243997568],"iteration":962,"passed_time":3.586840967,"remaining_time":0.1378121659},
{"learn":[0.2439915375],"iteration":963,"passed_time":3.590123579,"remaining_time":0.134071005},
{"learn":[0.243979948],"iteration":964,"passed_time":3.598248233,"remaining_time":0.1305064126},
{"learn":[0.2439768073],"iteration":965,"passed_time":3.602730689,"remaining_time":0.1268041857},
{"learn":[0.2439571864],"iteration":966,"passed_time":3.605785493,"remaining_time":0.1230516249},
{"learn":[0.2439291024],"iteration":967,"passed_time":3.609157459,"remaining_time":0.1193109904},
{"learn":[0.2439064779],"iteration":968,"passed_time":3.612345915,"remaining_time":0.115565246},
{"learn":[0.2438948265],"iteration":969,"passed_time":3.615950622,"remaining_time":0.1118335244},
{"learn":[0.2438901096],"iteration":970,"passed_time":3.623263172,"remaining_time":0.1082128033},
{"learn":[0.2438860902],"iteration":971,"passed_time":3.626596732,"remaining_time":0.1044698647},
{"learn":[0.2438807051],"iteration":972,"passed_time":3.63043628,"remaining_time":0.1007418084},
{"learn":[0.2438768164],"iteration":973,"passed_time":3.634899796,"remaining_time":0.09703017937},
{"learn":[0.2438641511],"iteration":974,"passed_time":3.638053051,"remaining_time":0.09328341157},
{"learn":[0.243859989],"iteration":975,"passed_time":3.64113149,"remaining_time":0.08953602025},
{"learn":[0.2438563968],"iteration":976,"passed_time":3.644456076,"remaining_time":0.08579579298},
{"learn":[0.2438425537],"iteration":977,"passed_time":3.648062634,"remaining_time":0.08206275864},
{"learn":[0.243834103],"iteration":978,"passed_time":3.652615534,"remaining_time":0.07835028213},
{"learn":[0.2438283358],"iteration":979,"passed_time":3.655666451,"remaining_time":0.07460543778},
{"learn":[0.2438169819],"iteration":980,"passed_time":3.6588335,"remaining_time":0.07086425739},
{"learn":[0.2438110159],"iteration":981,"passed_time":3.662292554,"remaining_time":0.06712959876},
{"learn":[0.2437843818],"iteration":982,"passed_time":3.665781406,"remaining_time":0.06339601617},
{"learn":[0.2437706811],"iteration":983,"passed_time":3.669317764,"remaining_time":0.05966370348},
{"learn":[0.2437594064],"iteration":984,"passed_time":3.672644454,"remaining_time":0.05592859575},
{"learn":[0.2437469786],"iteration":985,"passed_time":3.676174045,"remaining_time":0.0521971974},
{"learn":[0.2437363556],"iteration":986,"passed_time":3.680870515,"remaining_time":0.04848157719},
{"learn":[0.2437276438],"iteration":987,"passed_time":3.684063806,"remaining_time":0.04474571424},
{"learn":[0.2437181334],"iteration":988,"passed_time":3.687203187,"remaining_time":0.04101034889},
{"learn":[0.2437044824],"iteration":989,"passed_time":3.690674244,"remaining_time":0.03727953782},
{"learn":[0.2436998037],"iteration":990,"passed_time":3.699405955,"remaining_time":0.03359702684},
{"learn":[0.243675844],"iteration":991,"passed_time":3.702627705,"remaining_time":0.02985990085},
{"learn":[0.2436723024],"iteration":992,"passed_time":3.707712963,"remaining_time":0.02613694938},
{"learn":[0.2436682833],"iteration":993,"passed_time":3.711582111,"remaining_time":0.02240391616},
{"learn":[0.243664459],"iteration":994,"passed_time":3.714658673,"remaining_time":0.0186666265},
{"learn":[0.243653799],"iteration":995,"passed_time":3.718162557,"remaining_time":0.01493237975},
{"learn":[0.2436490982],"iteration":996,"passed_time":3.7217703,"remaining_time":0.01119890762},
{"learn":[0.2436263841],"iteration":997,"passed_time":3.725060405,"remaining_time":0.007465050911},
{"learn":[0.2436211109],"iteration":998,"passed_time":3.728761601,"remaining_time":0.003732494095},
{"learn":[0.243602748],"iteration":999,"passed_time":3.731986284,"remaining_time":0}
]}